{
	"kernelMeasures": [
		{
			"kernel": "CONV_2D",
			"executionTime": 211903,
			"startExecutionTime": 1562874037694,
			"endExecutionTime": 1562874037906
		},
		{
			"kernel": "MAX_POOL_2D",
			"executionTime": 26012,
			"startExecutionTime": 1562874037906,
			"endExecutionTime": 1562874037932
		},
		{
			"kernel": "CONV_2D",
			"executionTime": 5657,
			"startExecutionTime": 1562874037932,
			"endExecutionTime": 1562874037937
		},
		{
			"kernel": "CONV_2D",
			"executionTime": 4457,
			"startExecutionTime": 1562874037937,
			"endExecutionTime": 1562874037942
		},
		{
			"kernel": "CONV_2D",
			"executionTime": 40480,
			"startExecutionTime": 1562874037942,
			"endExecutionTime": 1562874037982
		},
		{
			"kernel": "CONCATENATION",
			"executionTime": 2405,
			"startExecutionTime": 1562874037982,
			"endExecutionTime": 1562874037985
		},
		{
			"kernel": "CONV_2D",
			"executionTime": 7528,
			"startExecutionTime": 1562874037985,
			"endExecutionTime": 1562874037992
		},
		{
			"kernel": "CONV_2D",
			"executionTime": 5610,
			"startExecutionTime": 1562874037992,
			"endExecutionTime": 1562874037998
		},
		{
			"kernel": "CONV_2D",
			"executionTime": 39449,
			"startExecutionTime": 1562874037998,
			"endExecutionTime": 1562874038037
		},
		{
			"kernel": "CONCATENATION",
			"executionTime": 2499,
			"startExecutionTime": 1562874038037,
			"endExecutionTime": 1562874038040
		},
		{
			"kernel": "CONV_2D",
			"executionTime": 10465,
			"startExecutionTime": 1562874038040,
			"endExecutionTime": 1562874038050
		},
		{
			"kernel": "CONV_2D",
			"executionTime": 11106,
			"startExecutionTime": 1562874038050,
			"endExecutionTime": 1562874038062
		},
		{
			"kernel": "CONV_2D",
			"executionTime": 96074,
			"startExecutionTime": 1562874038062,
			"endExecutionTime": 1562874038158
		},
		{
			"kernel": "CONCATENATION",
			"executionTime": 4197,
			"startExecutionTime": 1562874038158,
			"endExecutionTime": 1562874038162
		},
		{
			"kernel": "MAX_POOL_2D",
			"executionTime": 13043,
			"startExecutionTime": 1562874038162,
			"endExecutionTime": 1562874038175
		},
		{
			"kernel": "CONV_2D",
			"executionTime": 5558,
			"startExecutionTime": 1562874038175,
			"endExecutionTime": 1562874038180
		},
		{
			"kernel": "CONV_2D",
			"executionTime": 3794,
			"startExecutionTime": 1562874038181,
			"endExecutionTime": 1562874038184
		},
		{
			"kernel": "CONV_2D",
			"executionTime": 29378,
			"startExecutionTime": 1562874038184,
			"endExecutionTime": 1562874038214
		},
		{
			"kernel": "CONCATENATION",
			"executionTime": 1014,
			"startExecutionTime": 1562874038214,
			"endExecutionTime": 1562874038215
		},
		{
			"kernel": "CONV_2D",
			"executionTime": 6983,
			"startExecutionTime": 1562874038215,
			"endExecutionTime": 1562874038222
		},
		{
			"kernel": "CONV_2D",
			"executionTime": 5092,
			"startExecutionTime": 1562874038222,
			"endExecutionTime": 1562874038227
		},
		{
			"kernel": "CONV_2D",
			"executionTime": 52884,
			"startExecutionTime": 1562874038227,
			"endExecutionTime": 1562874038280
		},
		{
			"kernel": "CONCATENATION",
			"executionTime": 1502,
			"startExecutionTime": 1562874038280,
			"endExecutionTime": 1562874038281
		},
		{
			"kernel": "CONV_2D",
			"executionTime": 8976,
			"startExecutionTime": 1562874038281,
			"endExecutionTime": 1562874038290
		},
		{
			"kernel": "CONV_2D",
			"executionTime": 4923,
			"startExecutionTime": 1562874038290,
			"endExecutionTime": 1562874038295
		},
		{
			"kernel": "CONV_2D",
			"executionTime": 50679,
			"startExecutionTime": 1562874038295,
			"endExecutionTime": 1562874038346
		},
		{
			"kernel": "CONCATENATION",
			"executionTime": 1529,
			"startExecutionTime": 1562874038346,
			"endExecutionTime": 1562874038347
		},
		{
			"kernel": "CONV_2D",
			"executionTime": 11338,
			"startExecutionTime": 1562874038347,
			"endExecutionTime": 1562874038359
		},
		{
			"kernel": "CONV_2D",
			"executionTime": 7639,
			"startExecutionTime": 1562874038359,
			"endExecutionTime": 1562874038366
		},
		{
			"kernel": "CONV_2D",
			"executionTime": 76815,
			"startExecutionTime": 1562874038366,
			"endExecutionTime": 1562874038443
		},
		{
			"kernel": "CONCATENATION",
			"executionTime": 1946,
			"startExecutionTime": 1562874038443,
			"endExecutionTime": 1562874038445
		},
		{
			"kernel": "MAX_POOL_2D",
			"executionTime": 5752,
			"startExecutionTime": 1562874038445,
			"endExecutionTime": 1562874038451
		},
		{
			"kernel": "CONV_2D",
			"executionTime": 3201,
			"startExecutionTime": 1562874038451,
			"endExecutionTime": 1562874038454
		},
		{
			"kernel": "CONV_2D",
			"executionTime": 2105,
			"startExecutionTime": 1562874038454,
			"endExecutionTime": 1562874038456
		},
		{
			"kernel": "CONV_2D",
			"executionTime": 20144,
			"startExecutionTime": 1562874038456,
			"endExecutionTime": 1562874038477
		},
		{
			"kernel": "CONCATENATION",
			"executionTime": 411,
			"startExecutionTime": 1562874038477,
			"endExecutionTime": 1562874038477
		},
		{
			"kernel": "CONV_2D",
			"executionTime": 48408,
			"startExecutionTime": 1562874038477,
			"endExecutionTime": 1562874038525
		},
		{
			"kernel": "AVERAGE_POOL_2D",
			"executionTime": 1125,
			"startExecutionTime": 1562874038525,
			"endExecutionTime": 1562874038527
		},
		{
			"kernel": "RESHAPE",
			"executionTime": 5,
			"startExecutionTime": 1562874038527,
			"endExecutionTime": 1562874038527
		},
		{
			"kernel": "SOFTMAX",
			"executionTime": 268,
			"startExecutionTime": 1562874038527,
			"endExecutionTime": 1562874038527
		}
	],
	"inferenceTime": 833065,
	"startInferenceTime": 1562874037694,
	"endInferenceTime": 1562874038527
}
