{
	"kernelMeasures": [
		{
			"kernel": "CONV_2D",
			"executionTime": 208514,
			"startExecutionTime": 1562874599250,
			"endExecutionTime": 1562874599458
		},
		{
			"kernel": "MAX_POOL_2D",
			"executionTime": 25892,
			"startExecutionTime": 1562874599458,
			"endExecutionTime": 1562874599484
		},
		{
			"kernel": "CONV_2D",
			"executionTime": 5781,
			"startExecutionTime": 1562874599484,
			"endExecutionTime": 1562874599490
		},
		{
			"kernel": "CONV_2D",
			"executionTime": 4210,
			"startExecutionTime": 1562874599490,
			"endExecutionTime": 1562874599494
		},
		{
			"kernel": "CONV_2D",
			"executionTime": 40281,
			"startExecutionTime": 1562874599494,
			"endExecutionTime": 1562874599535
		},
		{
			"kernel": "CONCATENATION",
			"executionTime": 2400,
			"startExecutionTime": 1562874599535,
			"endExecutionTime": 1562874599537
		},
		{
			"kernel": "CONV_2D",
			"executionTime": 7168,
			"startExecutionTime": 1562874599537,
			"endExecutionTime": 1562874599544
		},
		{
			"kernel": "CONV_2D",
			"executionTime": 4356,
			"startExecutionTime": 1562874599544,
			"endExecutionTime": 1562874599549
		},
		{
			"kernel": "CONV_2D",
			"executionTime": 39318,
			"startExecutionTime": 1562874599549,
			"endExecutionTime": 1562874599588
		},
		{
			"kernel": "CONCATENATION",
			"executionTime": 2518,
			"startExecutionTime": 1562874599588,
			"endExecutionTime": 1562874599590
		},
		{
			"kernel": "CONV_2D",
			"executionTime": 9948,
			"startExecutionTime": 1562874599591,
			"endExecutionTime": 1562874599600
		},
		{
			"kernel": "CONV_2D",
			"executionTime": 10764,
			"startExecutionTime": 1562874599600,
			"endExecutionTime": 1562874599611
		},
		{
			"kernel": "CONV_2D",
			"executionTime": 96999,
			"startExecutionTime": 1562874599611,
			"endExecutionTime": 1562874599708
		},
		{
			"kernel": "CONCATENATION",
			"executionTime": 4243,
			"startExecutionTime": 1562874599708,
			"endExecutionTime": 1562874599713
		},
		{
			"kernel": "MAX_POOL_2D",
			"executionTime": 13182,
			"startExecutionTime": 1562874599713,
			"endExecutionTime": 1562874599726
		},
		{
			"kernel": "CONV_2D",
			"executionTime": 6214,
			"startExecutionTime": 1562874599726,
			"endExecutionTime": 1562874599732
		},
		{
			"kernel": "CONV_2D",
			"executionTime": 3785,
			"startExecutionTime": 1562874599732,
			"endExecutionTime": 1562874599736
		},
		{
			"kernel": "CONV_2D",
			"executionTime": 27784,
			"startExecutionTime": 1562874599736,
			"endExecutionTime": 1562874599764
		},
		{
			"kernel": "CONCATENATION",
			"executionTime": 1044,
			"startExecutionTime": 1562874599764,
			"endExecutionTime": 1562874599765
		},
		{
			"kernel": "CONV_2D",
			"executionTime": 6997,
			"startExecutionTime": 1562874599765,
			"endExecutionTime": 1562874599772
		},
		{
			"kernel": "CONV_2D",
			"executionTime": 5046,
			"startExecutionTime": 1562874599772,
			"endExecutionTime": 1562874599777
		},
		{
			"kernel": "CONV_2D",
			"executionTime": 51000,
			"startExecutionTime": 1562874599777,
			"endExecutionTime": 1562874599828
		},
		{
			"kernel": "CONCATENATION",
			"executionTime": 1698,
			"startExecutionTime": 1562874599828,
			"endExecutionTime": 1562874599829
		},
		{
			"kernel": "CONV_2D",
			"executionTime": 8813,
			"startExecutionTime": 1562874599829,
			"endExecutionTime": 1562874599838
		},
		{
			"kernel": "CONV_2D",
			"executionTime": 5184,
			"startExecutionTime": 1562874599838,
			"endExecutionTime": 1562874599843
		},
		{
			"kernel": "CONV_2D",
			"executionTime": 50928,
			"startExecutionTime": 1562874599843,
			"endExecutionTime": 1562874599894
		},
		{
			"kernel": "CONCATENATION",
			"executionTime": 1588,
			"startExecutionTime": 1562874599894,
			"endExecutionTime": 1562874599896
		},
		{
			"kernel": "CONV_2D",
			"executionTime": 11681,
			"startExecutionTime": 1562874599896,
			"endExecutionTime": 1562874599908
		},
		{
			"kernel": "CONV_2D",
			"executionTime": 7845,
			"startExecutionTime": 1562874599908,
			"endExecutionTime": 1562874599916
		},
		{
			"kernel": "CONV_2D",
			"executionTime": 77193,
			"startExecutionTime": 1562874599916,
			"endExecutionTime": 1562874599993
		},
		{
			"kernel": "CONCATENATION",
			"executionTime": 2128,
			"startExecutionTime": 1562874599993,
			"endExecutionTime": 1562874599995
		},
		{
			"kernel": "MAX_POOL_2D",
			"executionTime": 6003,
			"startExecutionTime": 1562874599995,
			"endExecutionTime": 1562874600001
		},
		{
			"kernel": "CONV_2D",
			"executionTime": 3296,
			"startExecutionTime": 1562874600001,
			"endExecutionTime": 1562874600004
		},
		{
			"kernel": "CONV_2D",
			"executionTime": 2244,
			"startExecutionTime": 1562874600004,
			"endExecutionTime": 1562874600007
		},
		{
			"kernel": "CONV_2D",
			"executionTime": 21114,
			"startExecutionTime": 1562874600007,
			"endExecutionTime": 1562874600028
		},
		{
			"kernel": "CONCATENATION",
			"executionTime": 412,
			"startExecutionTime": 1562874600028,
			"endExecutionTime": 1562874600028
		},
		{
			"kernel": "CONV_2D",
			"executionTime": 56633,
			"startExecutionTime": 1562874600028,
			"endExecutionTime": 1562874600085
		},
		{
			"kernel": "AVERAGE_POOL_2D",
			"executionTime": 1230,
			"startExecutionTime": 1562874600085,
			"endExecutionTime": 1562874600086
		},
		{
			"kernel": "RESHAPE",
			"executionTime": 5,
			"startExecutionTime": 1562874600086,
			"endExecutionTime": 1562874600086
		},
		{
			"kernel": "SOFTMAX",
			"executionTime": 270,
			"startExecutionTime": 1562874600086,
			"endExecutionTime": 1562874600086
		}
	],
	"inferenceTime": 836424,
	"startInferenceTime": 1562874599250,
	"endInferenceTime": 1562874600086
}
