{
	"kernelMeasures": [
		{
			"kernel": "CONV_2D",
			"executionTime": 71983,
			"startExecutionTime": 1561580736643,
			"endExecutionTime": 1561580736715
		},
		{
			"kernel": "CONV_2D",
			"executionTime": 413926,
			"startExecutionTime": 1561580736715,
			"endExecutionTime": 1561580737129
		},
		{
			"kernel": "CONV_2D",
			"executionTime": 503526,
			"startExecutionTime": 1561580737129,
			"endExecutionTime": 1561580737632
		},
		{
			"kernel": "MAX_POOL_2D",
			"executionTime": 31495,
			"startExecutionTime": 1561580737632,
			"endExecutionTime": 1561580737664
		},
		{
			"kernel": "CONV_2D",
			"executionTime": 20017,
			"startExecutionTime": 1561580737664,
			"endExecutionTime": 1561580737684
		},
		{
			"kernel": "CONV_2D",
			"executionTime": 480008,
			"startExecutionTime": 1561580737684,
			"endExecutionTime": 1561580738164
		},
		{
			"kernel": "MAX_POOL_2D",
			"executionTime": 17212,
			"startExecutionTime": 1561580738164,
			"endExecutionTime": 1561580738181
		},
		{
			"kernel": "CONV_2D",
			"executionTime": 12657,
			"startExecutionTime": 1561580738181,
			"endExecutionTime": 1561580738194
		},
		{
			"kernel": "CONV_2D",
			"executionTime": 10653,
			"startExecutionTime": 1561580738194,
			"endExecutionTime": 1561580738204
		},
		{
			"kernel": "CONV_2D",
			"executionTime": 124473,
			"startExecutionTime": 1561580738204,
			"endExecutionTime": 1561580738329
		},
		{
			"kernel": "CONV_2D",
			"executionTime": 9702,
			"startExecutionTime": 1561580738329,
			"endExecutionTime": 1561580738338
		},
		{
			"kernel": "CONV_2D",
			"executionTime": 70849,
			"startExecutionTime": 1561580738339,
			"endExecutionTime": 1561580738409
		},
		{
			"kernel": "CONV_2D",
			"executionTime": 103384,
			"startExecutionTime": 1561580738409,
			"endExecutionTime": 1561580738513
		},
		{
			"kernel": "AVERAGE_POOL_2D",
			"executionTime": 23698,
			"startExecutionTime": 1561580738513,
			"endExecutionTime": 1561580738536
		},
		{
			"kernel": "CONV_2D",
			"executionTime": 6062,
			"startExecutionTime": 1561580738537,
			"endExecutionTime": 1561580738543
		},
		{
			"kernel": "CONCATENATION",
			"executionTime": 2224,
			"startExecutionTime": 1561580738543,
			"endExecutionTime": 1561580738545
		},
		{
			"kernel": "CONV_2D",
			"executionTime": 13194,
			"startExecutionTime": 1561580738545,
			"endExecutionTime": 1561580738558
		},
		{
			"kernel": "CONV_2D",
			"executionTime": 10263,
			"startExecutionTime": 1561580738558,
			"endExecutionTime": 1561580738568
		},
		{
			"kernel": "CONV_2D",
			"executionTime": 124719,
			"startExecutionTime": 1561580738568,
			"endExecutionTime": 1561580738693
		},
		{
			"kernel": "CONV_2D",
			"executionTime": 12858,
			"startExecutionTime": 1561580738693,
			"endExecutionTime": 1561580738706
		},
		{
			"kernel": "CONV_2D",
			"executionTime": 71157,
			"startExecutionTime": 1561580738706,
			"endExecutionTime": 1561580738777
		},
		{
			"kernel": "CONV_2D",
			"executionTime": 105312,
			"startExecutionTime": 1561580738777,
			"endExecutionTime": 1561580738882
		},
		{
			"kernel": "AVERAGE_POOL_2D",
			"executionTime": 31014,
			"startExecutionTime": 1561580738882,
			"endExecutionTime": 1561580738913
		},
		{
			"kernel": "CONV_2D",
			"executionTime": 13212,
			"startExecutionTime": 1561580738913,
			"endExecutionTime": 1561580738927
		},
		{
			"kernel": "CONCATENATION",
			"executionTime": 2550,
			"startExecutionTime": 1561580738927,
			"endExecutionTime": 1561580738929
		},
		{
			"kernel": "CONV_2D",
			"executionTime": 13625,
			"startExecutionTime": 1561580738929,
			"endExecutionTime": 1561580738943
		},
		{
			"kernel": "CONV_2D",
			"executionTime": 11295,
			"startExecutionTime": 1561580738943,
			"endExecutionTime": 1561580738954
		},
		{
			"kernel": "CONV_2D",
			"executionTime": 123643,
			"startExecutionTime": 1561580738954,
			"endExecutionTime": 1561580739078
		},
		{
			"kernel": "CONV_2D",
			"executionTime": 13550,
			"startExecutionTime": 1561580739078,
			"endExecutionTime": 1561580739091
		},
		{
			"kernel": "CONV_2D",
			"executionTime": 75594,
			"startExecutionTime": 1561580739091,
			"endExecutionTime": 1561580739167
		},
		{
			"kernel": "CONV_2D",
			"executionTime": 106000,
			"startExecutionTime": 1561580739167,
			"endExecutionTime": 1561580739273
		},
		{
			"kernel": "AVERAGE_POOL_2D",
			"executionTime": 34526,
			"startExecutionTime": 1561580739273,
			"endExecutionTime": 1561580739308
		},
		{
			"kernel": "CONV_2D",
			"executionTime": 13783,
			"startExecutionTime": 1561580739308,
			"endExecutionTime": 1561580739321
		},
		{
			"kernel": "CONCATENATION",
			"executionTime": 2277,
			"startExecutionTime": 1561580739321,
			"endExecutionTime": 1561580739324
		},
		{
			"kernel": "CONV_2D",
			"executionTime": 167510,
			"startExecutionTime": 1561580739324,
			"endExecutionTime": 1561580739491
		},
		{
			"kernel": "CONV_2D",
			"executionTime": 13580,
			"startExecutionTime": 1561580739491,
			"endExecutionTime": 1561580739505
		},
		{
			"kernel": "CONV_2D",
			"executionTime": 70938,
			"startExecutionTime": 1561580739505,
			"endExecutionTime": 1561580739576
		},
		{
			"kernel": "CONV_2D",
			"executionTime": 26954,
			"startExecutionTime": 1561580739576,
			"endExecutionTime": 1561580739603
		},
		{
			"kernel": "MAX_POOL_2D",
			"executionTime": 5784,
			"startExecutionTime": 1561580739603,
			"endExecutionTime": 1561580739609
		},
		{
			"kernel": "CONCATENATION",
			"executionTime": 1143,
			"startExecutionTime": 1561580739609,
			"endExecutionTime": 1561580739610
		},
		{
			"kernel": "CONV_2D",
			"executionTime": 22573,
			"startExecutionTime": 1561580739610,
			"endExecutionTime": 1561580739632
		},
		{
			"kernel": "CONV_2D",
			"executionTime": 18872,
			"startExecutionTime": 1561580739632,
			"endExecutionTime": 1561580739651
		},
		{
			"kernel": "CONV_2D",
			"executionTime": 31311,
			"startExecutionTime": 1561580739651,
			"endExecutionTime": 1561580739683
		},
		{
			"kernel": "CONV_2D",
			"executionTime": 38731,
			"startExecutionTime": 1561580739683,
			"endExecutionTime": 1561580739721
		},
		{
			"kernel": "CONV_2D",
			"executionTime": 16793,
			"startExecutionTime": 1561580739721,
			"endExecutionTime": 1561580739738
		},
		{
			"kernel": "CONV_2D",
			"executionTime": 29681,
			"startExecutionTime": 1561580739738,
			"endExecutionTime": 1561580739768
		},
		{
			"kernel": "CONV_2D",
			"executionTime": 30571,
			"startExecutionTime": 1561580739768,
			"endExecutionTime": 1561580739798
		},
		{
			"kernel": "CONV_2D",
			"executionTime": 30147,
			"startExecutionTime": 1561580739798,
			"endExecutionTime": 1561580739829
		},
		{
			"kernel": "CONV_2D",
			"executionTime": 38019,
			"startExecutionTime": 1561580739829,
			"endExecutionTime": 1561580739867
		},
		{
			"kernel": "AVERAGE_POOL_2D",
			"executionTime": 20633,
			"startExecutionTime": 1561580739867,
			"endExecutionTime": 1561580739887
		},
		{
			"kernel": "CONV_2D",
			"executionTime": 24376,
			"startExecutionTime": 1561580739887,
			"endExecutionTime": 1561580739912
		},
		{
			"kernel": "CONCATENATION",
			"executionTime": 1092,
			"startExecutionTime": 1561580739912,
			"endExecutionTime": 1561580739913
		},
		{
			"kernel": "CONV_2D",
			"executionTime": 24681,
			"startExecutionTime": 1561580739913,
			"endExecutionTime": 1561580739938
		},
		{
			"kernel": "CONV_2D",
			"executionTime": 20537,
			"startExecutionTime": 1561580739938,
			"endExecutionTime": 1561580739958
		},
		{
			"kernel": "CONV_2D",
			"executionTime": 50423,
			"startExecutionTime": 1561580739958,
			"endExecutionTime": 1561580740008
		},
		{
			"kernel": "CONV_2D",
			"executionTime": 44853,
			"startExecutionTime": 1561580740009,
			"endExecutionTime": 1561580740053
		},
		{
			"kernel": "CONV_2D",
			"executionTime": 19758,
			"startExecutionTime": 1561580740053,
			"endExecutionTime": 1561580740073
		},
		{
			"kernel": "CONV_2D",
			"executionTime": 41389,
			"startExecutionTime": 1561580740073,
			"endExecutionTime": 1561580740115
		},
		{
			"kernel": "CONV_2D",
			"executionTime": 41379,
			"startExecutionTime": 1561580740115,
			"endExecutionTime": 1561580740156
		},
		{
			"kernel": "CONV_2D",
			"executionTime": 41634,
			"startExecutionTime": 1561580740156,
			"endExecutionTime": 1561580740198
		},
		{
			"kernel": "CONV_2D",
			"executionTime": 50871,
			"startExecutionTime": 1561580740198,
			"endExecutionTime": 1561580740248
		},
		{
			"kernel": "AVERAGE_POOL_2D",
			"executionTime": 21140,
			"startExecutionTime": 1561580740249,
			"endExecutionTime": 1561580740270
		},
		{
			"kernel": "CONV_2D",
			"executionTime": 24213,
			"startExecutionTime": 1561580740270,
			"endExecutionTime": 1561580740294
		},
		{
			"kernel": "CONCATENATION",
			"executionTime": 1195,
			"startExecutionTime": 1561580740294,
			"endExecutionTime": 1561580740295
		},
		{
			"kernel": "CONV_2D",
			"executionTime": 24765,
			"startExecutionTime": 1561580740295,
			"endExecutionTime": 1561580740320
		},
		{
			"kernel": "CONV_2D",
			"executionTime": 21088,
			"startExecutionTime": 1561580740320,
			"endExecutionTime": 1561580740341
		},
		{
			"kernel": "CONV_2D",
			"executionTime": 41695,
			"startExecutionTime": 1561580740341,
			"endExecutionTime": 1561580740383
		},
		{
			"kernel": "CONV_2D",
			"executionTime": 47135,
			"startExecutionTime": 1561580740383,
			"endExecutionTime": 1561580740430
		},
		{
			"kernel": "CONV_2D",
			"executionTime": 21431,
			"startExecutionTime": 1561580740430,
			"endExecutionTime": 1561580740451
		},
		{
			"kernel": "CONV_2D",
			"executionTime": 45873,
			"startExecutionTime": 1561580740451,
			"endExecutionTime": 1561580740497
		},
		{
			"kernel": "CONV_2D",
			"executionTime": 41753,
			"startExecutionTime": 1561580740497,
			"endExecutionTime": 1561580740539
		},
		{
			"kernel": "CONV_2D",
			"executionTime": 41077,
			"startExecutionTime": 1561580740539,
			"endExecutionTime": 1561580740580
		},
		{
			"kernel": "CONV_2D",
			"executionTime": 45390,
			"startExecutionTime": 1561580740580,
			"endExecutionTime": 1561580740626
		},
		{
			"kernel": "AVERAGE_POOL_2D",
			"executionTime": 20580,
			"startExecutionTime": 1561580740626,
			"endExecutionTime": 1561580740646
		},
		{
			"kernel": "CONV_2D",
			"executionTime": 22684,
			"startExecutionTime": 1561580740646,
			"endExecutionTime": 1561580740669
		},
		{
			"kernel": "CONCATENATION",
			"executionTime": 1077,
			"startExecutionTime": 1561580740669,
			"endExecutionTime": 1561580740670
		},
		{
			"kernel": "CONV_2D",
			"executionTime": 29325,
			"startExecutionTime": 1561580740670,
			"endExecutionTime": 1561580740699
		},
		{
			"kernel": "CONV_2D",
			"executionTime": 25936,
			"startExecutionTime": 1561580740699,
			"endExecutionTime": 1561580740725
		},
		{
			"kernel": "CONV_2D",
			"executionTime": 57035,
			"startExecutionTime": 1561580740725,
			"endExecutionTime": 1561580740782
		},
		{
			"kernel": "CONV_2D",
			"executionTime": 54856,
			"startExecutionTime": 1561580740782,
			"endExecutionTime": 1561580740837
		},
		{
			"kernel": "CONV_2D",
			"executionTime": 24885,
			"startExecutionTime": 1561580740837,
			"endExecutionTime": 1561580740862
		},
		{
			"kernel": "CONV_2D",
			"executionTime": 57713,
			"startExecutionTime": 1561580740862,
			"endExecutionTime": 1561580740920
		},
		{
			"kernel": "CONV_2D",
			"executionTime": 55013,
			"startExecutionTime": 1561580740920,
			"endExecutionTime": 1561580740975
		},
		{
			"kernel": "CONV_2D",
			"executionTime": 56303,
			"startExecutionTime": 1561580740975,
			"endExecutionTime": 1561580741031
		},
		{
			"kernel": "CONV_2D",
			"executionTime": 55025,
			"startExecutionTime": 1561580741031,
			"endExecutionTime": 1561580741086
		},
		{
			"kernel": "AVERAGE_POOL_2D",
			"executionTime": 21146,
			"startExecutionTime": 1561580741086,
			"endExecutionTime": 1561580741107
		},
		{
			"kernel": "CONV_2D",
			"executionTime": 23684,
			"startExecutionTime": 1561580741107,
			"endExecutionTime": 1561580741131
		},
		{
			"kernel": "CONCATENATION",
			"executionTime": 1273,
			"startExecutionTime": 1561580741131,
			"endExecutionTime": 1561580741132
		},
		{
			"kernel": "CONV_2D",
			"executionTime": 25473,
			"startExecutionTime": 1561580741132,
			"endExecutionTime": 1561580741158
		},
		{
			"kernel": "CONV_2D",
			"executionTime": 29681,
			"startExecutionTime": 1561580741158,
			"endExecutionTime": 1561580741188
		},
		{
			"kernel": "CONV_2D",
			"executionTime": 23733,
			"startExecutionTime": 1561580741188,
			"endExecutionTime": 1561580741211
		},
		{
			"kernel": "CONV_2D",
			"executionTime": 54678,
			"startExecutionTime": 1561580741211,
			"endExecutionTime": 1561580741266
		},
		{
			"kernel": "CONV_2D",
			"executionTime": 58487,
			"startExecutionTime": 1561580741266,
			"endExecutionTime": 1561580741325
		},
		{
			"kernel": "CONV_2D",
			"executionTime": 21001,
			"startExecutionTime": 1561580741325,
			"endExecutionTime": 1561580741346
		},
		{
			"kernel": "MAX_POOL_2D",
			"executionTime": 3434,
			"startExecutionTime": 1561580741346,
			"endExecutionTime": 1561580741349
		},
		{
			"kernel": "CONCATENATION",
			"executionTime": 325,
			"startExecutionTime": 1561580741349,
			"endExecutionTime": 1561580741349
		},
		{
			"kernel": "CONV_2D",
			"executionTime": 20459,
			"startExecutionTime": 1561580741349,
			"endExecutionTime": 1561580741370
		},
		{
			"kernel": "CONV_2D",
			"executionTime": 22211,
			"startExecutionTime": 1561580741370,
			"endExecutionTime": 1561580741392
		},
		{
			"kernel": "CONV_2D",
			"executionTime": 22938,
			"startExecutionTime": 1561580741392,
			"endExecutionTime": 1561580741415
		},
		{
			"kernel": "CONV_2D",
			"executionTime": 22796,
			"startExecutionTime": 1561580741415,
			"endExecutionTime": 1561580741438
		},
		{
			"kernel": "CONCATENATION",
			"executionTime": 220,
			"startExecutionTime": 1561580741438,
			"endExecutionTime": 1561580741438
		},
		{
			"kernel": "CONV_2D",
			"executionTime": 25007,
			"startExecutionTime": 1561580741438,
			"endExecutionTime": 1561580741463
		},
		{
			"kernel": "CONV_2D",
			"executionTime": 78074,
			"startExecutionTime": 1561580741463,
			"endExecutionTime": 1561580741541
		},
		{
			"kernel": "CONV_2D",
			"executionTime": 27292,
			"startExecutionTime": 1561580741541,
			"endExecutionTime": 1561580741568
		},
		{
			"kernel": "CONV_2D",
			"executionTime": 23037,
			"startExecutionTime": 1561580741568,
			"endExecutionTime": 1561580741592
		},
		{
			"kernel": "CONCATENATION",
			"executionTime": 215,
			"startExecutionTime": 1561580741592,
			"endExecutionTime": 1561580741592
		},
		{
			"kernel": "AVERAGE_POOL_2D",
			"executionTime": 7254,
			"startExecutionTime": 1561580741592,
			"endExecutionTime": 1561580741599
		},
		{
			"kernel": "CONV_2D",
			"executionTime": 11018,
			"startExecutionTime": 1561580741599,
			"endExecutionTime": 1561580741610
		},
		{
			"kernel": "CONCATENATION",
			"executionTime": 638,
			"startExecutionTime": 1561580741610,
			"endExecutionTime": 1561580741611
		},
		{
			"kernel": "CONV_2D",
			"executionTime": 27448,
			"startExecutionTime": 1561580741611,
			"endExecutionTime": 1561580741638
		},
		{
			"kernel": "CONV_2D",
			"executionTime": 35338,
			"startExecutionTime": 1561580741638,
			"endExecutionTime": 1561580741674
		},
		{
			"kernel": "CONV_2D",
			"executionTime": 22860,
			"startExecutionTime": 1561580741674,
			"endExecutionTime": 1561580741696
		},
		{
			"kernel": "CONV_2D",
			"executionTime": 26096,
			"startExecutionTime": 1561580741696,
			"endExecutionTime": 1561580741723
		},
		{
			"kernel": "CONCATENATION",
			"executionTime": 231,
			"startExecutionTime": 1561580741723,
			"endExecutionTime": 1561580741723
		},
		{
			"kernel": "CONV_2D",
			"executionTime": 38909,
			"startExecutionTime": 1561580741723,
			"endExecutionTime": 1561580741762
		},
		{
			"kernel": "CONV_2D",
			"executionTime": 74245,
			"startExecutionTime": 1561580741762,
			"endExecutionTime": 1561580741836
		},
		{
			"kernel": "CONV_2D",
			"executionTime": 25097,
			"startExecutionTime": 1561580741836,
			"endExecutionTime": 1561580741861
		},
		{
			"kernel": "CONV_2D",
			"executionTime": 22835,
			"startExecutionTime": 1561580741861,
			"endExecutionTime": 1561580741884
		},
		{
			"kernel": "CONCATENATION",
			"executionTime": 326,
			"startExecutionTime": 1561580741884,
			"endExecutionTime": 1561580741884
		},
		{
			"kernel": "AVERAGE_POOL_2D",
			"executionTime": 11640,
			"startExecutionTime": 1561580741884,
			"endExecutionTime": 1561580741896
		},
		{
			"kernel": "CONV_2D",
			"executionTime": 16587,
			"startExecutionTime": 1561580741896,
			"endExecutionTime": 1561580741913
		},
		{
			"kernel": "CONCATENATION",
			"executionTime": 742,
			"startExecutionTime": 1561580741913,
			"endExecutionTime": 1561580741913
		},
		{
			"kernel": "AVERAGE_POOL_2D",
			"executionTime": 821,
			"startExecutionTime": 1561580741913,
			"endExecutionTime": 1561580741914
		},
		{
			"kernel": "CONV_2D",
			"executionTime": 33329,
			"startExecutionTime": 1561580741914,
			"endExecutionTime": 1561580741947
		},
		{
			"kernel": "RESHAPE",
			"executionTime": 6,
			"startExecutionTime": 1561580741948,
			"endExecutionTime": 1561580741948
		},
		{
			"kernel": "SOFTMAX",
			"executionTime": 269,
			"startExecutionTime": 1561580741948,
			"endExecutionTime": 1561580741948
		}
	],
	"inferenceTime": 5305169,
	"startInferenceTime": 1561580736643,
	"endInferenceTime": 1561580741948
}
