{
	"kernelMeasures": [
		{
			"kernel": "CONV_2D",
			"executionTime": 72250,
			"startExecutionTime": 1561596278372,
			"endExecutionTime": 1561596278444
		},
		{
			"kernel": "CONV_2D",
			"executionTime": 414606,
			"startExecutionTime": 1561596278444,
			"endExecutionTime": 1561596278859
		},
		{
			"kernel": "CONV_2D",
			"executionTime": 509052,
			"startExecutionTime": 1561596278859,
			"endExecutionTime": 1561596279368
		},
		{
			"kernel": "MAX_POOL_2D",
			"executionTime": 31464,
			"startExecutionTime": 1561596279368,
			"endExecutionTime": 1561596279399
		},
		{
			"kernel": "CONV_2D",
			"executionTime": 20495,
			"startExecutionTime": 1561596279399,
			"endExecutionTime": 1561596279420
		},
		{
			"kernel": "CONV_2D",
			"executionTime": 474851,
			"startExecutionTime": 1561596279420,
			"endExecutionTime": 1561596279895
		},
		{
			"kernel": "MAX_POOL_2D",
			"executionTime": 17138,
			"startExecutionTime": 1561596279895,
			"endExecutionTime": 1561596279912
		},
		{
			"kernel": "CONV_2D",
			"executionTime": 10741,
			"startExecutionTime": 1561596279912,
			"endExecutionTime": 1561596279922
		},
		{
			"kernel": "CONV_2D",
			"executionTime": 7478,
			"startExecutionTime": 1561596279922,
			"endExecutionTime": 1561596279930
		},
		{
			"kernel": "CONV_2D",
			"executionTime": 122927,
			"startExecutionTime": 1561596279930,
			"endExecutionTime": 1561596280053
		},
		{
			"kernel": "CONV_2D",
			"executionTime": 11084,
			"startExecutionTime": 1561596280053,
			"endExecutionTime": 1561596280064
		},
		{
			"kernel": "CONV_2D",
			"executionTime": 72097,
			"startExecutionTime": 1561596280064,
			"endExecutionTime": 1561596280136
		},
		{
			"kernel": "CONV_2D",
			"executionTime": 105257,
			"startExecutionTime": 1561596280136,
			"endExecutionTime": 1561596280241
		},
		{
			"kernel": "AVERAGE_POOL_2D",
			"executionTime": 23759,
			"startExecutionTime": 1561596280241,
			"endExecutionTime": 1561596280265
		},
		{
			"kernel": "CONV_2D",
			"executionTime": 6699,
			"startExecutionTime": 1561596280265,
			"endExecutionTime": 1561596280272
		},
		{
			"kernel": "CONCATENATION",
			"executionTime": 2152,
			"startExecutionTime": 1561596280272,
			"endExecutionTime": 1561596280274
		},
		{
			"kernel": "CONV_2D",
			"executionTime": 12935,
			"startExecutionTime": 1561596280274,
			"endExecutionTime": 1561596280287
		},
		{
			"kernel": "CONV_2D",
			"executionTime": 10341,
			"startExecutionTime": 1561596280287,
			"endExecutionTime": 1561596280297
		},
		{
			"kernel": "CONV_2D",
			"executionTime": 125972,
			"startExecutionTime": 1561596280297,
			"endExecutionTime": 1561596280423
		},
		{
			"kernel": "CONV_2D",
			"executionTime": 13312,
			"startExecutionTime": 1561596280423,
			"endExecutionTime": 1561596280437
		},
		{
			"kernel": "CONV_2D",
			"executionTime": 71621,
			"startExecutionTime": 1561596280437,
			"endExecutionTime": 1561596280508
		},
		{
			"kernel": "CONV_2D",
			"executionTime": 104375,
			"startExecutionTime": 1561596280508,
			"endExecutionTime": 1561596280613
		},
		{
			"kernel": "AVERAGE_POOL_2D",
			"executionTime": 31060,
			"startExecutionTime": 1561596280613,
			"endExecutionTime": 1561596280644
		},
		{
			"kernel": "CONV_2D",
			"executionTime": 13106,
			"startExecutionTime": 1561596280644,
			"endExecutionTime": 1561596280657
		},
		{
			"kernel": "CONCATENATION",
			"executionTime": 2349,
			"startExecutionTime": 1561596280657,
			"endExecutionTime": 1561596280659
		},
		{
			"kernel": "CONV_2D",
			"executionTime": 13290,
			"startExecutionTime": 1561596280659,
			"endExecutionTime": 1561596280673
		},
		{
			"kernel": "CONV_2D",
			"executionTime": 10880,
			"startExecutionTime": 1561596280673,
			"endExecutionTime": 1561596280684
		},
		{
			"kernel": "CONV_2D",
			"executionTime": 124516,
			"startExecutionTime": 1561596280684,
			"endExecutionTime": 1561596280808
		},
		{
			"kernel": "CONV_2D",
			"executionTime": 13394,
			"startExecutionTime": 1561596280808,
			"endExecutionTime": 1561596280821
		},
		{
			"kernel": "CONV_2D",
			"executionTime": 71339,
			"startExecutionTime": 1561596280821,
			"endExecutionTime": 1561596280893
		},
		{
			"kernel": "CONV_2D",
			"executionTime": 104402,
			"startExecutionTime": 1561596280893,
			"endExecutionTime": 1561596280997
		},
		{
			"kernel": "AVERAGE_POOL_2D",
			"executionTime": 33957,
			"startExecutionTime": 1561596280997,
			"endExecutionTime": 1561596281031
		},
		{
			"kernel": "CONV_2D",
			"executionTime": 13553,
			"startExecutionTime": 1561596281031,
			"endExecutionTime": 1561596281045
		},
		{
			"kernel": "CONCATENATION",
			"executionTime": 3370,
			"startExecutionTime": 1561596281045,
			"endExecutionTime": 1561596281048
		},
		{
			"kernel": "CONV_2D",
			"executionTime": 176406,
			"startExecutionTime": 1561596281048,
			"endExecutionTime": 1561596281225
		},
		{
			"kernel": "CONV_2D",
			"executionTime": 13559,
			"startExecutionTime": 1561596281225,
			"endExecutionTime": 1561596281238
		},
		{
			"kernel": "CONV_2D",
			"executionTime": 71136,
			"startExecutionTime": 1561596281238,
			"endExecutionTime": 1561596281309
		},
		{
			"kernel": "CONV_2D",
			"executionTime": 25658,
			"startExecutionTime": 1561596281309,
			"endExecutionTime": 1561596281335
		},
		{
			"kernel": "MAX_POOL_2D",
			"executionTime": 5658,
			"startExecutionTime": 1561596281335,
			"endExecutionTime": 1561596281341
		},
		{
			"kernel": "CONCATENATION",
			"executionTime": 1052,
			"startExecutionTime": 1561596281341,
			"endExecutionTime": 1561596281342
		},
		{
			"kernel": "CONV_2D",
			"executionTime": 24064,
			"startExecutionTime": 1561596281342,
			"endExecutionTime": 1561596281366
		},
		{
			"kernel": "CONV_2D",
			"executionTime": 17349,
			"startExecutionTime": 1561596281366,
			"endExecutionTime": 1561596281383
		},
		{
			"kernel": "CONV_2D",
			"executionTime": 31298,
			"startExecutionTime": 1561596281383,
			"endExecutionTime": 1561596281415
		},
		{
			"kernel": "CONV_2D",
			"executionTime": 38285,
			"startExecutionTime": 1561596281415,
			"endExecutionTime": 1561596281453
		},
		{
			"kernel": "CONV_2D",
			"executionTime": 17349,
			"startExecutionTime": 1561596281453,
			"endExecutionTime": 1561596281470
		},
		{
			"kernel": "CONV_2D",
			"executionTime": 30379,
			"startExecutionTime": 1561596281470,
			"endExecutionTime": 1561596281501
		},
		{
			"kernel": "CONV_2D",
			"executionTime": 30517,
			"startExecutionTime": 1561596281501,
			"endExecutionTime": 1561596281531
		},
		{
			"kernel": "CONV_2D",
			"executionTime": 29615,
			"startExecutionTime": 1561596281531,
			"endExecutionTime": 1561596281561
		},
		{
			"kernel": "CONV_2D",
			"executionTime": 36964,
			"startExecutionTime": 1561596281561,
			"endExecutionTime": 1561596281598
		},
		{
			"kernel": "AVERAGE_POOL_2D",
			"executionTime": 20367,
			"startExecutionTime": 1561596281598,
			"endExecutionTime": 1561596281618
		},
		{
			"kernel": "CONV_2D",
			"executionTime": 24303,
			"startExecutionTime": 1561596281618,
			"endExecutionTime": 1561596281642
		},
		{
			"kernel": "CONCATENATION",
			"executionTime": 1110,
			"startExecutionTime": 1561596281642,
			"endExecutionTime": 1561596281644
		},
		{
			"kernel": "CONV_2D",
			"executionTime": 33123,
			"startExecutionTime": 1561596281644,
			"endExecutionTime": 1561596281677
		},
		{
			"kernel": "CONV_2D",
			"executionTime": 22160,
			"startExecutionTime": 1561596281677,
			"endExecutionTime": 1561596281699
		},
		{
			"kernel": "CONV_2D",
			"executionTime": 43847,
			"startExecutionTime": 1561596281699,
			"endExecutionTime": 1561596281743
		},
		{
			"kernel": "CONV_2D",
			"executionTime": 46582,
			"startExecutionTime": 1561596281743,
			"endExecutionTime": 1561596281789
		},
		{
			"kernel": "CONV_2D",
			"executionTime": 20781,
			"startExecutionTime": 1561596281789,
			"endExecutionTime": 1561596281810
		},
		{
			"kernel": "CONV_2D",
			"executionTime": 41618,
			"startExecutionTime": 1561596281810,
			"endExecutionTime": 1561596281852
		},
		{
			"kernel": "CONV_2D",
			"executionTime": 42472,
			"startExecutionTime": 1561596281852,
			"endExecutionTime": 1561596281894
		},
		{
			"kernel": "CONV_2D",
			"executionTime": 42253,
			"startExecutionTime": 1561596281894,
			"endExecutionTime": 1561596281937
		},
		{
			"kernel": "CONV_2D",
			"executionTime": 56183,
			"startExecutionTime": 1561596281937,
			"endExecutionTime": 1561596281993
		},
		{
			"kernel": "AVERAGE_POOL_2D",
			"executionTime": 20208,
			"startExecutionTime": 1561596281993,
			"endExecutionTime": 1561596282013
		},
		{
			"kernel": "CONV_2D",
			"executionTime": 24666,
			"startExecutionTime": 1561596282013,
			"endExecutionTime": 1561596282038
		},
		{
			"kernel": "CONCATENATION",
			"executionTime": 1150,
			"startExecutionTime": 1561596282038,
			"endExecutionTime": 1561596282039
		},
		{
			"kernel": "CONV_2D",
			"executionTime": 23954,
			"startExecutionTime": 1561596282039,
			"endExecutionTime": 1561596282063
		},
		{
			"kernel": "CONV_2D",
			"executionTime": 20460,
			"startExecutionTime": 1561596282063,
			"endExecutionTime": 1561596282083
		},
		{
			"kernel": "CONV_2D",
			"executionTime": 42630,
			"startExecutionTime": 1561596282083,
			"endExecutionTime": 1561596282126
		},
		{
			"kernel": "CONV_2D",
			"executionTime": 46946,
			"startExecutionTime": 1561596282126,
			"endExecutionTime": 1561596282173
		},
		{
			"kernel": "CONV_2D",
			"executionTime": 21069,
			"startExecutionTime": 1561596282173,
			"endExecutionTime": 1561596282194
		},
		{
			"kernel": "CONV_2D",
			"executionTime": 44793,
			"startExecutionTime": 1561596282194,
			"endExecutionTime": 1561596282239
		},
		{
			"kernel": "CONV_2D",
			"executionTime": 42816,
			"startExecutionTime": 1561596282239,
			"endExecutionTime": 1561596282282
		},
		{
			"kernel": "CONV_2D",
			"executionTime": 42229,
			"startExecutionTime": 1561596282282,
			"endExecutionTime": 1561596282324
		},
		{
			"kernel": "CONV_2D",
			"executionTime": 48193,
			"startExecutionTime": 1561596282324,
			"endExecutionTime": 1561596282372
		},
		{
			"kernel": "AVERAGE_POOL_2D",
			"executionTime": 20244,
			"startExecutionTime": 1561596282372,
			"endExecutionTime": 1561596282392
		},
		{
			"kernel": "CONV_2D",
			"executionTime": 24666,
			"startExecutionTime": 1561596282392,
			"endExecutionTime": 1561596282417
		},
		{
			"kernel": "CONCATENATION",
			"executionTime": 1083,
			"startExecutionTime": 1561596282417,
			"endExecutionTime": 1561596282418
		},
		{
			"kernel": "CONV_2D",
			"executionTime": 24691,
			"startExecutionTime": 1561596282418,
			"endExecutionTime": 1561596282443
		},
		{
			"kernel": "CONV_2D",
			"executionTime": 24226,
			"startExecutionTime": 1561596282443,
			"endExecutionTime": 1561596282467
		},
		{
			"kernel": "CONV_2D",
			"executionTime": 55998,
			"startExecutionTime": 1561596282467,
			"endExecutionTime": 1561596282523
		},
		{
			"kernel": "CONV_2D",
			"executionTime": 55613,
			"startExecutionTime": 1561596282523,
			"endExecutionTime": 1561596282579
		},
		{
			"kernel": "CONV_2D",
			"executionTime": 29486,
			"startExecutionTime": 1561596282579,
			"endExecutionTime": 1561596282608
		},
		{
			"kernel": "CONV_2D",
			"executionTime": 55019,
			"startExecutionTime": 1561596282608,
			"endExecutionTime": 1561596282663
		},
		{
			"kernel": "CONV_2D",
			"executionTime": 57302,
			"startExecutionTime": 1561596282663,
			"endExecutionTime": 1561596282721
		},
		{
			"kernel": "CONV_2D",
			"executionTime": 57657,
			"startExecutionTime": 1561596282721,
			"endExecutionTime": 1561596282778
		},
		{
			"kernel": "CONV_2D",
			"executionTime": 53949,
			"startExecutionTime": 1561596282778,
			"endExecutionTime": 1561596282832
		},
		{
			"kernel": "AVERAGE_POOL_2D",
			"executionTime": 20308,
			"startExecutionTime": 1561596282832,
			"endExecutionTime": 1561596282853
		},
		{
			"kernel": "CONV_2D",
			"executionTime": 23801,
			"startExecutionTime": 1561596282853,
			"endExecutionTime": 1561596282876
		},
		{
			"kernel": "CONCATENATION",
			"executionTime": 1174,
			"startExecutionTime": 1561596282876,
			"endExecutionTime": 1561596282878
		},
		{
			"kernel": "CONV_2D",
			"executionTime": 24616,
			"startExecutionTime": 1561596282878,
			"endExecutionTime": 1561596282902
		},
		{
			"kernel": "CONV_2D",
			"executionTime": 28703,
			"startExecutionTime": 1561596282902,
			"endExecutionTime": 1561596282931
		},
		{
			"kernel": "CONV_2D",
			"executionTime": 24127,
			"startExecutionTime": 1561596282931,
			"endExecutionTime": 1561596282955
		},
		{
			"kernel": "CONV_2D",
			"executionTime": 59886,
			"startExecutionTime": 1561596282955,
			"endExecutionTime": 1561596283015
		},
		{
			"kernel": "CONV_2D",
			"executionTime": 55261,
			"startExecutionTime": 1561596283015,
			"endExecutionTime": 1561596283070
		},
		{
			"kernel": "CONV_2D",
			"executionTime": 19865,
			"startExecutionTime": 1561596283070,
			"endExecutionTime": 1561596283090
		},
		{
			"kernel": "MAX_POOL_2D",
			"executionTime": 3082,
			"startExecutionTime": 1561596283090,
			"endExecutionTime": 1561596283093
		},
		{
			"kernel": "CONCATENATION",
			"executionTime": 341,
			"startExecutionTime": 1561596283093,
			"endExecutionTime": 1561596283094
		},
		{
			"kernel": "CONV_2D",
			"executionTime": 18309,
			"startExecutionTime": 1561596283094,
			"endExecutionTime": 1561596283112
		},
		{
			"kernel": "CONV_2D",
			"executionTime": 23029,
			"startExecutionTime": 1561596283112,
			"endExecutionTime": 1561596283135
		},
		{
			"kernel": "CONV_2D",
			"executionTime": 22860,
			"startExecutionTime": 1561596283135,
			"endExecutionTime": 1561596283158
		},
		{
			"kernel": "CONV_2D",
			"executionTime": 22497,
			"startExecutionTime": 1561596283158,
			"endExecutionTime": 1561596283180
		},
		{
			"kernel": "CONCATENATION",
			"executionTime": 212,
			"startExecutionTime": 1561596283180,
			"endExecutionTime": 1561596283181
		},
		{
			"kernel": "CONV_2D",
			"executionTime": 28777,
			"startExecutionTime": 1561596283181,
			"endExecutionTime": 1561596283209
		},
		{
			"kernel": "CONV_2D",
			"executionTime": 89255,
			"startExecutionTime": 1561596283209,
			"endExecutionTime": 1561596283299
		},
		{
			"kernel": "CONV_2D",
			"executionTime": 23412,
			"startExecutionTime": 1561596283299,
			"endExecutionTime": 1561596283322
		},
		{
			"kernel": "CONV_2D",
			"executionTime": 23758,
			"startExecutionTime": 1561596283322,
			"endExecutionTime": 1561596283346
		},
		{
			"kernel": "CONCATENATION",
			"executionTime": 218,
			"startExecutionTime": 1561596283346,
			"endExecutionTime": 1561596283346
		},
		{
			"kernel": "AVERAGE_POOL_2D",
			"executionTime": 7178,
			"startExecutionTime": 1561596283346,
			"endExecutionTime": 1561596283353
		},
		{
			"kernel": "CONV_2D",
			"executionTime": 10159,
			"startExecutionTime": 1561596283353,
			"endExecutionTime": 1561596283364
		},
		{
			"kernel": "CONCATENATION",
			"executionTime": 756,
			"startExecutionTime": 1561596283364,
			"endExecutionTime": 1561596283364
		},
		{
			"kernel": "CONV_2D",
			"executionTime": 29378,
			"startExecutionTime": 1561596283364,
			"endExecutionTime": 1561596283394
		},
		{
			"kernel": "CONV_2D",
			"executionTime": 35184,
			"startExecutionTime": 1561596283394,
			"endExecutionTime": 1561596283429
		},
		{
			"kernel": "CONV_2D",
			"executionTime": 23118,
			"startExecutionTime": 1561596283429,
			"endExecutionTime": 1561596283452
		},
		{
			"kernel": "CONV_2D",
			"executionTime": 25297,
			"startExecutionTime": 1561596283452,
			"endExecutionTime": 1561596283477
		},
		{
			"kernel": "CONCATENATION",
			"executionTime": 214,
			"startExecutionTime": 1561596283477,
			"endExecutionTime": 1561596283478
		},
		{
			"kernel": "CONV_2D",
			"executionTime": 37861,
			"startExecutionTime": 1561596283478,
			"endExecutionTime": 1561596283515
		},
		{
			"kernel": "CONV_2D",
			"executionTime": 80559,
			"startExecutionTime": 1561596283515,
			"endExecutionTime": 1561596283596
		},
		{
			"kernel": "CONV_2D",
			"executionTime": 25986,
			"startExecutionTime": 1561596283596,
			"endExecutionTime": 1561596283622
		},
		{
			"kernel": "CONV_2D",
			"executionTime": 25090,
			"startExecutionTime": 1561596283622,
			"endExecutionTime": 1561596283647
		},
		{
			"kernel": "CONCATENATION",
			"executionTime": 240,
			"startExecutionTime": 1561596283647,
			"endExecutionTime": 1561596283647
		},
		{
			"kernel": "AVERAGE_POOL_2D",
			"executionTime": 11242,
			"startExecutionTime": 1561596283647,
			"endExecutionTime": 1561596283659
		},
		{
			"kernel": "CONV_2D",
			"executionTime": 15974,
			"startExecutionTime": 1561596283659,
			"endExecutionTime": 1561596283675
		},
		{
			"kernel": "CONCATENATION",
			"executionTime": 725,
			"startExecutionTime": 1561596283675,
			"endExecutionTime": 1561596283675
		},
		{
			"kernel": "AVERAGE_POOL_2D",
			"executionTime": 806,
			"startExecutionTime": 1561596283675,
			"endExecutionTime": 1561596283676
		},
		{
			"kernel": "CONV_2D",
			"executionTime": 32022,
			"startExecutionTime": 1561596283676,
			"endExecutionTime": 1561596283708
		},
		{
			"kernel": "RESHAPE",
			"executionTime": 5,
			"startExecutionTime": 1561596283708,
			"endExecutionTime": 1561596283708
		},
		{
			"kernel": "SOFTMAX",
			"executionTime": 266,
			"startExecutionTime": 1561596283708,
			"endExecutionTime": 1561596283709
		}
	],
	"inferenceTime": 5336809,
	"startInferenceTime": 1561596278372,
	"endInferenceTime": 1561596283709
}
