{
	"kernelMeasures": [
		{
			"kernel": "CONV_2D",
			"executionTime": 20986,
			"startExecutionTime": 1561584213938,
			"endExecutionTime": 1561584213959
		},
		{
			"kernel": "DEPTHWISE_CONV_2D",
			"executionTime": 31456,
			"startExecutionTime": 1561584213959,
			"endExecutionTime": 1561584213991
		},
		{
			"kernel": "CONV_2D",
			"executionTime": 24074,
			"startExecutionTime": 1561584213991,
			"endExecutionTime": 1561584214015
		},
		{
			"kernel": "DEPTHWISE_CONV_2D",
			"executionTime": 14348,
			"startExecutionTime": 1561584214015,
			"endExecutionTime": 1561584214029
		},
		{
			"kernel": "CONV_2D",
			"executionTime": 14218,
			"startExecutionTime": 1561584214029,
			"endExecutionTime": 1561584214044
		},
		{
			"kernel": "DEPTHWISE_CONV_2D",
			"executionTime": 26650,
			"startExecutionTime": 1561584214044,
			"endExecutionTime": 1561584214070
		},
		{
			"kernel": "CONV_2D",
			"executionTime": 18341,
			"startExecutionTime": 1561584214070,
			"endExecutionTime": 1561584214089
		},
		{
			"kernel": "DEPTHWISE_CONV_2D",
			"executionTime": 7010,
			"startExecutionTime": 1561584214089,
			"endExecutionTime": 1561584214096
		},
		{
			"kernel": "CONV_2D",
			"executionTime": 9401,
			"startExecutionTime": 1561584214096,
			"endExecutionTime": 1561584214105
		},
		{
			"kernel": "DEPTHWISE_CONV_2D",
			"executionTime": 12885,
			"startExecutionTime": 1561584214105,
			"endExecutionTime": 1561584214118
		},
		{
			"kernel": "CONV_2D",
			"executionTime": 14132,
			"startExecutionTime": 1561584214118,
			"endExecutionTime": 1561584214132
		},
		{
			"kernel": "DEPTHWISE_CONV_2D",
			"executionTime": 3285,
			"startExecutionTime": 1561584214132,
			"endExecutionTime": 1561584214135
		},
		{
			"kernel": "CONV_2D",
			"executionTime": 6855,
			"startExecutionTime": 1561584214135,
			"endExecutionTime": 1561584214142
		},
		{
			"kernel": "DEPTHWISE_CONV_2D",
			"executionTime": 6167,
			"startExecutionTime": 1561584214142,
			"endExecutionTime": 1561584214148
		},
		{
			"kernel": "CONV_2D",
			"executionTime": 11741,
			"startExecutionTime": 1561584214148,
			"endExecutionTime": 1561584214160
		},
		{
			"kernel": "DEPTHWISE_CONV_2D",
			"executionTime": 5840,
			"startExecutionTime": 1561584214160,
			"endExecutionTime": 1561584214166
		},
		{
			"kernel": "CONV_2D",
			"executionTime": 11830,
			"startExecutionTime": 1561584214166,
			"endExecutionTime": 1561584214178
		},
		{
			"kernel": "DEPTHWISE_CONV_2D",
			"executionTime": 6019,
			"startExecutionTime": 1561584214178,
			"endExecutionTime": 1561584214184
		},
		{
			"kernel": "CONV_2D",
			"executionTime": 11653,
			"startExecutionTime": 1561584214184,
			"endExecutionTime": 1561584214196
		},
		{
			"kernel": "DEPTHWISE_CONV_2D",
			"executionTime": 5971,
			"startExecutionTime": 1561584214196,
			"endExecutionTime": 1561584214202
		},
		{
			"kernel": "CONV_2D",
			"executionTime": 11673,
			"startExecutionTime": 1561584214202,
			"endExecutionTime": 1561584214213
		},
		{
			"kernel": "DEPTHWISE_CONV_2D",
			"executionTime": 6115,
			"startExecutionTime": 1561584214213,
			"endExecutionTime": 1561584214219
		},
		{
			"kernel": "CONV_2D",
			"executionTime": 11663,
			"startExecutionTime": 1561584214219,
			"endExecutionTime": 1561584214231
		},
		{
			"kernel": "DEPTHWISE_CONV_2D",
			"executionTime": 1565,
			"startExecutionTime": 1561584214231,
			"endExecutionTime": 1561584214233
		},
		{
			"kernel": "CONV_2D",
			"executionTime": 6507,
			"startExecutionTime": 1561584214233,
			"endExecutionTime": 1561584214239
		},
		{
			"kernel": "DEPTHWISE_CONV_2D",
			"executionTime": 2704,
			"startExecutionTime": 1561584214239,
			"endExecutionTime": 1561584214242
		},
		{
			"kernel": "CONV_2D",
			"executionTime": 11587,
			"startExecutionTime": 1561584214242,
			"endExecutionTime": 1561584214253
		},
		{
			"kernel": "AVERAGE_POOL_2D",
			"executionTime": 177,
			"startExecutionTime": 1561584214254,
			"endExecutionTime": 1561584214254
		},
		{
			"kernel": "CONV_2D",
			"executionTime": 2079,
			"startExecutionTime": 1561584214254,
			"endExecutionTime": 1561584214256
		},
		{
			"kernel": "RESHAPE",
			"executionTime": 4,
			"startExecutionTime": 1561584214256,
			"endExecutionTime": 1561584214256
		},
		{
			"kernel": "SOFTMAX",
			"executionTime": 126,
			"startExecutionTime": 1561584214256,
			"endExecutionTime": 1561584214256
		}
	],
	"inferenceTime": 317496,
	"startInferenceTime": 1561584213938,
	"endInferenceTime": 1561584214256
}
