{
	"kernelMeasures": [
		{
			"kernel": "CONV_2D",
			"executionTime": 22313,
			"startExecutionTime": 1561584665840,
			"endExecutionTime": 1561584665862
		},
		{
			"kernel": "DEPTHWISE_CONV_2D",
			"executionTime": 35271,
			"startExecutionTime": 1561584665862,
			"endExecutionTime": 1561584665898
		},
		{
			"kernel": "CONV_2D",
			"executionTime": 24943,
			"startExecutionTime": 1561584665898,
			"endExecutionTime": 1561584665923
		},
		{
			"kernel": "DEPTHWISE_CONV_2D",
			"executionTime": 16180,
			"startExecutionTime": 1561584665923,
			"endExecutionTime": 1561584665939
		},
		{
			"kernel": "CONV_2D",
			"executionTime": 14605,
			"startExecutionTime": 1561584665939,
			"endExecutionTime": 1561584665953
		},
		{
			"kernel": "DEPTHWISE_CONV_2D",
			"executionTime": 29935,
			"startExecutionTime": 1561584665953,
			"endExecutionTime": 1561584665983
		},
		{
			"kernel": "CONV_2D",
			"executionTime": 19027,
			"startExecutionTime": 1561584665983,
			"endExecutionTime": 1561584666002
		},
		{
			"kernel": "DEPTHWISE_CONV_2D",
			"executionTime": 8028,
			"startExecutionTime": 1561584666002,
			"endExecutionTime": 1561584666010
		},
		{
			"kernel": "CONV_2D",
			"executionTime": 9825,
			"startExecutionTime": 1561584666010,
			"endExecutionTime": 1561584666020
		},
		{
			"kernel": "DEPTHWISE_CONV_2D",
			"executionTime": 14436,
			"startExecutionTime": 1561584666020,
			"endExecutionTime": 1561584666035
		},
		{
			"kernel": "CONV_2D",
			"executionTime": 14679,
			"startExecutionTime": 1561584666035,
			"endExecutionTime": 1561584666049
		},
		{
			"kernel": "DEPTHWISE_CONV_2D",
			"executionTime": 3749,
			"startExecutionTime": 1561584666049,
			"endExecutionTime": 1561584666053
		},
		{
			"kernel": "CONV_2D",
			"executionTime": 7151,
			"startExecutionTime": 1561584666053,
			"endExecutionTime": 1561584666060
		},
		{
			"kernel": "DEPTHWISE_CONV_2D",
			"executionTime": 6919,
			"startExecutionTime": 1561584666060,
			"endExecutionTime": 1561584666067
		},
		{
			"kernel": "CONV_2D",
			"executionTime": 12124,
			"startExecutionTime": 1561584666067,
			"endExecutionTime": 1561584666079
		},
		{
			"kernel": "DEPTHWISE_CONV_2D",
			"executionTime": 6632,
			"startExecutionTime": 1561584666079,
			"endExecutionTime": 1561584666086
		},
		{
			"kernel": "CONV_2D",
			"executionTime": 12177,
			"startExecutionTime": 1561584666086,
			"endExecutionTime": 1561584666098
		},
		{
			"kernel": "DEPTHWISE_CONV_2D",
			"executionTime": 6778,
			"startExecutionTime": 1561584666098,
			"endExecutionTime": 1561584666105
		},
		{
			"kernel": "CONV_2D",
			"executionTime": 12224,
			"startExecutionTime": 1561584666105,
			"endExecutionTime": 1561584666117
		},
		{
			"kernel": "DEPTHWISE_CONV_2D",
			"executionTime": 6526,
			"startExecutionTime": 1561584666117,
			"endExecutionTime": 1561584666124
		},
		{
			"kernel": "CONV_2D",
			"executionTime": 12212,
			"startExecutionTime": 1561584666124,
			"endExecutionTime": 1561584666136
		},
		{
			"kernel": "DEPTHWISE_CONV_2D",
			"executionTime": 6912,
			"startExecutionTime": 1561584666136,
			"endExecutionTime": 1561584666143
		},
		{
			"kernel": "CONV_2D",
			"executionTime": 12162,
			"startExecutionTime": 1561584666143,
			"endExecutionTime": 1561584666155
		},
		{
			"kernel": "DEPTHWISE_CONV_2D",
			"executionTime": 1901,
			"startExecutionTime": 1561584666155,
			"endExecutionTime": 1561584666157
		},
		{
			"kernel": "CONV_2D",
			"executionTime": 6650,
			"startExecutionTime": 1561584666157,
			"endExecutionTime": 1561584666164
		},
		{
			"kernel": "DEPTHWISE_CONV_2D",
			"executionTime": 3059,
			"startExecutionTime": 1561584666164,
			"endExecutionTime": 1561584666167
		},
		{
			"kernel": "CONV_2D",
			"executionTime": 12326,
			"startExecutionTime": 1561584666167,
			"endExecutionTime": 1561584666179
		},
		{
			"kernel": "AVERAGE_POOL_2D",
			"executionTime": 187,
			"startExecutionTime": 1561584666179,
			"endExecutionTime": 1561584666179
		},
		{
			"kernel": "CONV_2D",
			"executionTime": 2384,
			"startExecutionTime": 1561584666179,
			"endExecutionTime": 1561584666182
		},
		{
			"kernel": "RESHAPE",
			"executionTime": 5,
			"startExecutionTime": 1561584666182,
			"endExecutionTime": 1561584666182
		},
		{
			"kernel": "SOFTMAX",
			"executionTime": 127,
			"startExecutionTime": 1561584666182,
			"endExecutionTime": 1561584666182
		}
	],
	"inferenceTime": 341938,
	"startInferenceTime": 1561584665840,
	"endInferenceTime": 1561584666182
}
