{
	"kernelMeasures": [
		{
			"kernel": "CONV_2D",
			"executionTime": 21460,
			"startExecutionTime": 1560378511519,
			"endExecutionTime": 1560378511540
		},
		{
			"kernel": "DEPTHWISE_CONV_2D",
			"executionTime": 31514,
			"startExecutionTime": 1560378511540,
			"endExecutionTime": 1560378511572
		},
		{
			"kernel": "CONV_2D",
			"executionTime": 25081,
			"startExecutionTime": 1560378511572,
			"endExecutionTime": 1560378511597
		},
		{
			"kernel": "DEPTHWISE_CONV_2D",
			"executionTime": 14267,
			"startExecutionTime": 1560378511597,
			"endExecutionTime": 1560378511611
		},
		{
			"kernel": "CONV_2D",
			"executionTime": 14996,
			"startExecutionTime": 1560378511611,
			"endExecutionTime": 1560378511626
		},
		{
			"kernel": "DEPTHWISE_CONV_2D",
			"executionTime": 26563,
			"startExecutionTime": 1560378511626,
			"endExecutionTime": 1560378511653
		},
		{
			"kernel": "CONV_2D",
			"executionTime": 18863,
			"startExecutionTime": 1560378511653,
			"endExecutionTime": 1560378511672
		},
		{
			"kernel": "DEPTHWISE_CONV_2D",
			"executionTime": 7037,
			"startExecutionTime": 1560378511672,
			"endExecutionTime": 1560378511679
		},
		{
			"kernel": "CONV_2D",
			"executionTime": 9787,
			"startExecutionTime": 1560378511679,
			"endExecutionTime": 1560378511688
		},
		{
			"kernel": "DEPTHWISE_CONV_2D",
			"executionTime": 12804,
			"startExecutionTime": 1560378511689,
			"endExecutionTime": 1560378511701
		},
		{
			"kernel": "CONV_2D",
			"executionTime": 14678,
			"startExecutionTime": 1560378511701,
			"endExecutionTime": 1560378511716
		},
		{
			"kernel": "DEPTHWISE_CONV_2D",
			"executionTime": 3301,
			"startExecutionTime": 1560378511716,
			"endExecutionTime": 1560378511719
		},
		{
			"kernel": "CONV_2D",
			"executionTime": 6930,
			"startExecutionTime": 1560378511719,
			"endExecutionTime": 1560378511726
		},
		{
			"kernel": "DEPTHWISE_CONV_2D",
			"executionTime": 6043,
			"startExecutionTime": 1560378511726,
			"endExecutionTime": 1560378511732
		},
		{
			"kernel": "CONV_2D",
			"executionTime": 11997,
			"startExecutionTime": 1560378511732,
			"endExecutionTime": 1560378511744
		},
		{
			"kernel": "DEPTHWISE_CONV_2D",
			"executionTime": 5916,
			"startExecutionTime": 1560378511744,
			"endExecutionTime": 1560378511750
		},
		{
			"kernel": "CONV_2D",
			"executionTime": 12069,
			"startExecutionTime": 1560378511750,
			"endExecutionTime": 1560378511762
		},
		{
			"kernel": "DEPTHWISE_CONV_2D",
			"executionTime": 6146,
			"startExecutionTime": 1560378511762,
			"endExecutionTime": 1560378511769
		},
		{
			"kernel": "CONV_2D",
			"executionTime": 12033,
			"startExecutionTime": 1560378511769,
			"endExecutionTime": 1560378511781
		},
		{
			"kernel": "DEPTHWISE_CONV_2D",
			"executionTime": 6061,
			"startExecutionTime": 1560378511781,
			"endExecutionTime": 1560378511787
		},
		{
			"kernel": "CONV_2D",
			"executionTime": 12044,
			"startExecutionTime": 1560378511787,
			"endExecutionTime": 1560378511799
		},
		{
			"kernel": "DEPTHWISE_CONV_2D",
			"executionTime": 6033,
			"startExecutionTime": 1560378511799,
			"endExecutionTime": 1560378511805
		},
		{
			"kernel": "CONV_2D",
			"executionTime": 12086,
			"startExecutionTime": 1560378511805,
			"endExecutionTime": 1560378511817
		},
		{
			"kernel": "DEPTHWISE_CONV_2D",
			"executionTime": 1599,
			"startExecutionTime": 1560378511817,
			"endExecutionTime": 1560378511818
		},
		{
			"kernel": "CONV_2D",
			"executionTime": 6660,
			"startExecutionTime": 1560378511818,
			"endExecutionTime": 1560378511825
		},
		{
			"kernel": "DEPTHWISE_CONV_2D",
			"executionTime": 2757,
			"startExecutionTime": 1560378511825,
			"endExecutionTime": 1560378511828
		},
		{
			"kernel": "CONV_2D",
			"executionTime": 12130,
			"startExecutionTime": 1560378511828,
			"endExecutionTime": 1560378511840
		},
		{
			"kernel": "AVERAGE_POOL_2D",
			"executionTime": 181,
			"startExecutionTime": 1560378511840,
			"endExecutionTime": 1560378511840
		},
		{
			"kernel": "CONV_2D",
			"executionTime": 2445,
			"startExecutionTime": 1560378511840,
			"endExecutionTime": 1560378511843
		},
		{
			"kernel": "RESHAPE",
			"executionTime": 4,
			"startExecutionTime": 1560378511843,
			"endExecutionTime": 1560378511843
		},
		{
			"kernel": "SOFTMAX",
			"executionTime": 125,
			"startExecutionTime": 1560378511843,
			"endExecutionTime": 1560378511843
		}
	],
	"inferenceTime": 324053,
	"startInferenceTime": 1560378511519,
	"endInferenceTime": 1560378511843
}
