{
	"kernelMeasures": [
		{
			"kernel": "CONV_2D",
			"executionTime": 23026,
			"startExecutionTime": 1562871569821,
			"endExecutionTime": 1562871569844
		},
		{
			"kernel": "DEPTHWISE_CONV_2D",
			"executionTime": 36706,
			"startExecutionTime": 1562871569844,
			"endExecutionTime": 1562871569880
		},
		{
			"kernel": "CONV_2D",
			"executionTime": 6755,
			"startExecutionTime": 1562871569880,
			"endExecutionTime": 1562871569887
		},
		{
			"kernel": "CONV_2D",
			"executionTime": 34309,
			"startExecutionTime": 1562871569887,
			"endExecutionTime": 1562871569921
		},
		{
			"kernel": "DEPTHWISE_CONV_2D",
			"executionTime": 24504,
			"startExecutionTime": 1562871569921,
			"endExecutionTime": 1562871569946
		},
		{
			"kernel": "CONV_2D",
			"executionTime": 3651,
			"startExecutionTime": 1562871569946,
			"endExecutionTime": 1562871569950
		},
		{
			"kernel": "CONV_2D",
			"executionTime": 14499,
			"startExecutionTime": 1562871569950,
			"endExecutionTime": 1562871569964
		},
		{
			"kernel": "DEPTHWISE_CONV_2D",
			"executionTime": 32851,
			"startExecutionTime": 1562871569964,
			"endExecutionTime": 1562871569997
		},
		{
			"kernel": "CONV_2D",
			"executionTime": 4617,
			"startExecutionTime": 1562871569997,
			"endExecutionTime": 1562871570002
		},
		{
			"kernel": "ADD",
			"executionTime": 29948,
			"startExecutionTime": 1562871570002,
			"endExecutionTime": 1562871570032
		},
		{
			"kernel": "CONV_2D",
			"executionTime": 14490,
			"startExecutionTime": 1562871570032,
			"endExecutionTime": 1562871570046
		},
		{
			"kernel": "DEPTHWISE_CONV_2D",
			"executionTime": 8611,
			"startExecutionTime": 1562871570046,
			"endExecutionTime": 1562871570055
		},
		{
			"kernel": "CONV_2D",
			"executionTime": 1456,
			"startExecutionTime": 1562871570055,
			"endExecutionTime": 1562871570056
		},
		{
			"kernel": "CONV_2D",
			"executionTime": 4854,
			"startExecutionTime": 1562871570056,
			"endExecutionTime": 1562871570061
		},
		{
			"kernel": "DEPTHWISE_CONV_2D",
			"executionTime": 11065,
			"startExecutionTime": 1562871570061,
			"endExecutionTime": 1562871570072
		},
		{
			"kernel": "CONV_2D",
			"executionTime": 1862,
			"startExecutionTime": 1562871570072,
			"endExecutionTime": 1562871570074
		},
		{
			"kernel": "ADD",
			"executionTime": 9977,
			"startExecutionTime": 1562871570074,
			"endExecutionTime": 1562871570084
		},
		{
			"kernel": "CONV_2D",
			"executionTime": 4623,
			"startExecutionTime": 1562871570084,
			"endExecutionTime": 1562871570089
		},
		{
			"kernel": "DEPTHWISE_CONV_2D",
			"executionTime": 11027,
			"startExecutionTime": 1562871570089,
			"endExecutionTime": 1562871570100
		},
		{
			"kernel": "CONV_2D",
			"executionTime": 1696,
			"startExecutionTime": 1562871570100,
			"endExecutionTime": 1562871570102
		},
		{
			"kernel": "ADD",
			"executionTime": 9988,
			"startExecutionTime": 1562871570102,
			"endExecutionTime": 1562871570112
		},
		{
			"kernel": "CONV_2D",
			"executionTime": 4603,
			"startExecutionTime": 1562871570112,
			"endExecutionTime": 1562871570116
		},
		{
			"kernel": "DEPTHWISE_CONV_2D",
			"executionTime": 2869,
			"startExecutionTime": 1562871570116,
			"endExecutionTime": 1562871570119
		},
		{
			"kernel": "CONV_2D",
			"executionTime": 1110,
			"startExecutionTime": 1562871570119,
			"endExecutionTime": 1562871570120
		},
		{
			"kernel": "CONV_2D",
			"executionTime": 2793,
			"startExecutionTime": 1562871570120,
			"endExecutionTime": 1562871570123
		},
		{
			"kernel": "DEPTHWISE_CONV_2D",
			"executionTime": 5181,
			"startExecutionTime": 1562871570123,
			"endExecutionTime": 1562871570128
		},
		{
			"kernel": "CONV_2D",
			"executionTime": 1575,
			"startExecutionTime": 1562871570128,
			"endExecutionTime": 1562871570130
		},
		{
			"kernel": "ADD",
			"executionTime": 4891,
			"startExecutionTime": 1562871570130,
			"endExecutionTime": 1562871570135
		},
		{
			"kernel": "CONV_2D",
			"executionTime": 2766,
			"startExecutionTime": 1562871570135,
			"endExecutionTime": 1562871570137
		},
		{
			"kernel": "DEPTHWISE_CONV_2D",
			"executionTime": 5310,
			"startExecutionTime": 1562871570137,
			"endExecutionTime": 1562871570143
		},
		{
			"kernel": "CONV_2D",
			"executionTime": 1420,
			"startExecutionTime": 1562871570143,
			"endExecutionTime": 1562871570144
		},
		{
			"kernel": "ADD",
			"executionTime": 4845,
			"startExecutionTime": 1562871570144,
			"endExecutionTime": 1562871570149
		},
		{
			"kernel": "CONV_2D",
			"executionTime": 2850,
			"startExecutionTime": 1562871570149,
			"endExecutionTime": 1562871570152
		},
		{
			"kernel": "DEPTHWISE_CONV_2D",
			"executionTime": 5118,
			"startExecutionTime": 1562871570152,
			"endExecutionTime": 1562871570157
		},
		{
			"kernel": "CONV_2D",
			"executionTime": 1448,
			"startExecutionTime": 1562871570157,
			"endExecutionTime": 1562871570158
		},
		{
			"kernel": "ADD",
			"executionTime": 4989,
			"startExecutionTime": 1562871570158,
			"endExecutionTime": 1562871570163
		},
		{
			"kernel": "CONV_2D",
			"executionTime": 2713,
			"startExecutionTime": 1562871570163,
			"endExecutionTime": 1562871570166
		},
		{
			"kernel": "DEPTHWISE_CONV_2D",
			"executionTime": 5179,
			"startExecutionTime": 1562871570166,
			"endExecutionTime": 1562871570171
		},
		{
			"kernel": "CONV_2D",
			"executionTime": 2122,
			"startExecutionTime": 1562871570171,
			"endExecutionTime": 1562871570173
		},
		{
			"kernel": "CONV_2D",
			"executionTime": 4800,
			"startExecutionTime": 1562871570173,
			"endExecutionTime": 1562871570178
		},
		{
			"kernel": "DEPTHWISE_CONV_2D",
			"executionTime": 7706,
			"startExecutionTime": 1562871570178,
			"endExecutionTime": 1562871570186
		},
		{
			"kernel": "CONV_2D",
			"executionTime": 2994,
			"startExecutionTime": 1562871570186,
			"endExecutionTime": 1562871570189
		},
		{
			"kernel": "ADD",
			"executionTime": 7466,
			"startExecutionTime": 1562871570189,
			"endExecutionTime": 1562871570197
		},
		{
			"kernel": "CONV_2D",
			"executionTime": 4936,
			"startExecutionTime": 1562871570197,
			"endExecutionTime": 1562871570201
		},
		{
			"kernel": "DEPTHWISE_CONV_2D",
			"executionTime": 7675,
			"startExecutionTime": 1562871570201,
			"endExecutionTime": 1562871570209
		},
		{
			"kernel": "CONV_2D",
			"executionTime": 3071,
			"startExecutionTime": 1562871570209,
			"endExecutionTime": 1562871570212
		},
		{
			"kernel": "ADD",
			"executionTime": 7606,
			"startExecutionTime": 1562871570212,
			"endExecutionTime": 1562871570220
		},
		{
			"kernel": "CONV_2D",
			"executionTime": 4682,
			"startExecutionTime": 1562871570220,
			"endExecutionTime": 1562871570225
		},
		{
			"kernel": "DEPTHWISE_CONV_2D",
			"executionTime": 1905,
			"startExecutionTime": 1562871570225,
			"endExecutionTime": 1562871570226
		},
		{
			"kernel": "CONV_2D",
			"executionTime": 1350,
			"startExecutionTime": 1562871570226,
			"endExecutionTime": 1562871570228
		},
		{
			"kernel": "CONV_2D",
			"executionTime": 2951,
			"startExecutionTime": 1562871570228,
			"endExecutionTime": 1562871570231
		},
		{
			"kernel": "DEPTHWISE_CONV_2D",
			"executionTime": 2924,
			"startExecutionTime": 1562871570231,
			"endExecutionTime": 1562871570234
		},
		{
			"kernel": "CONV_2D",
			"executionTime": 2137,
			"startExecutionTime": 1562871570234,
			"endExecutionTime": 1562871570236
		},
		{
			"kernel": "ADD",
			"executionTime": 3096,
			"startExecutionTime": 1562871570236,
			"endExecutionTime": 1562871570239
		},
		{
			"kernel": "CONV_2D",
			"executionTime": 2841,
			"startExecutionTime": 1562871570239,
			"endExecutionTime": 1562871570242
		},
		{
			"kernel": "DEPTHWISE_CONV_2D",
			"executionTime": 2975,
			"startExecutionTime": 1562871570242,
			"endExecutionTime": 1562871570245
		},
		{
			"kernel": "CONV_2D",
			"executionTime": 2215,
			"startExecutionTime": 1562871570245,
			"endExecutionTime": 1562871570247
		},
		{
			"kernel": "ADD",
			"executionTime": 3141,
			"startExecutionTime": 1562871570247,
			"endExecutionTime": 1562871570250
		},
		{
			"kernel": "CONV_2D",
			"executionTime": 2807,
			"startExecutionTime": 1562871570250,
			"endExecutionTime": 1562871570253
		},
		{
			"kernel": "DEPTHWISE_CONV_2D",
			"executionTime": 2934,
			"startExecutionTime": 1562871570253,
			"endExecutionTime": 1562871570256
		},
		{
			"kernel": "CONV_2D",
			"executionTime": 4046,
			"startExecutionTime": 1562871570256,
			"endExecutionTime": 1562871570260
		},
		{
			"kernel": "CONV_2D",
			"executionTime": 5667,
			"startExecutionTime": 1562871570260,
			"endExecutionTime": 1562871570266
		},
		{
			"kernel": "AVERAGE_POOL_2D",
			"executionTime": 212,
			"startExecutionTime": 1562871570266,
			"endExecutionTime": 1562871570266
		},
		{
			"kernel": "CONV_2D",
			"executionTime": 2576,
			"startExecutionTime": 1562871570266,
			"endExecutionTime": 1562871570268
		},
		{
			"kernel": "RESHAPE",
			"executionTime": 4,
			"startExecutionTime": 1562871570268,
			"endExecutionTime": 1562871570268
		}
	],
	"inferenceTime": 447890,
	"startInferenceTime": 1562871569821,
	"endInferenceTime": 1562871570269
}
