{
	"kernelMeasures": [
		{
			"kernel": "CONV_2D",
			"executionTime": 21626,
			"startExecutionTime": 1562869318612,
			"endExecutionTime": 1562869318634
		},
		{
			"kernel": "DEPTHWISE_CONV_2D",
			"executionTime": 32647,
			"startExecutionTime": 1562869318634,
			"endExecutionTime": 1562869318667
		},
		{
			"kernel": "CONV_2D",
			"executionTime": 6743,
			"startExecutionTime": 1562869318667,
			"endExecutionTime": 1562869318673
		},
		{
			"kernel": "CONV_2D",
			"executionTime": 33151,
			"startExecutionTime": 1562869318673,
			"endExecutionTime": 1562869318707
		},
		{
			"kernel": "DEPTHWISE_CONV_2D",
			"executionTime": 21914,
			"startExecutionTime": 1562869318707,
			"endExecutionTime": 1562869318728
		},
		{
			"kernel": "CONV_2D",
			"executionTime": 3517,
			"startExecutionTime": 1562869318728,
			"endExecutionTime": 1562869318732
		},
		{
			"kernel": "CONV_2D",
			"executionTime": 14020,
			"startExecutionTime": 1562869318732,
			"endExecutionTime": 1562869318746
		},
		{
			"kernel": "DEPTHWISE_CONV_2D",
			"executionTime": 29390,
			"startExecutionTime": 1562869318746,
			"endExecutionTime": 1562869318775
		},
		{
			"kernel": "CONV_2D",
			"executionTime": 4469,
			"startExecutionTime": 1562869318775,
			"endExecutionTime": 1562869318780
		},
		{
			"kernel": "ADD",
			"executionTime": 26871,
			"startExecutionTime": 1562869318780,
			"endExecutionTime": 1562869318807
		},
		{
			"kernel": "CONV_2D",
			"executionTime": 14015,
			"startExecutionTime": 1562869318807,
			"endExecutionTime": 1562869318821
		},
		{
			"kernel": "DEPTHWISE_CONV_2D",
			"executionTime": 7562,
			"startExecutionTime": 1562869318821,
			"endExecutionTime": 1562869318828
		},
		{
			"kernel": "CONV_2D",
			"executionTime": 1739,
			"startExecutionTime": 1562869318828,
			"endExecutionTime": 1562869318830
		},
		{
			"kernel": "CONV_2D",
			"executionTime": 4553,
			"startExecutionTime": 1562869318830,
			"endExecutionTime": 1562869318835
		},
		{
			"kernel": "DEPTHWISE_CONV_2D",
			"executionTime": 9884,
			"startExecutionTime": 1562869318835,
			"endExecutionTime": 1562869318845
		},
		{
			"kernel": "CONV_2D",
			"executionTime": 1714,
			"startExecutionTime": 1562869318845,
			"endExecutionTime": 1562869318846
		},
		{
			"kernel": "ADD",
			"executionTime": 8965,
			"startExecutionTime": 1562869318846,
			"endExecutionTime": 1562869318855
		},
		{
			"kernel": "CONV_2D",
			"executionTime": 4608,
			"startExecutionTime": 1562869318855,
			"endExecutionTime": 1562869318860
		},
		{
			"kernel": "DEPTHWISE_CONV_2D",
			"executionTime": 9603,
			"startExecutionTime": 1562869318860,
			"endExecutionTime": 1562869318870
		},
		{
			"kernel": "CONV_2D",
			"executionTime": 1669,
			"startExecutionTime": 1562869318870,
			"endExecutionTime": 1562869318871
		},
		{
			"kernel": "ADD",
			"executionTime": 8963,
			"startExecutionTime": 1562869318871,
			"endExecutionTime": 1562869318880
		},
		{
			"kernel": "CONV_2D",
			"executionTime": 4562,
			"startExecutionTime": 1562869318880,
			"endExecutionTime": 1562869318885
		},
		{
			"kernel": "DEPTHWISE_CONV_2D",
			"executionTime": 2761,
			"startExecutionTime": 1562869318885,
			"endExecutionTime": 1562869318888
		},
		{
			"kernel": "CONV_2D",
			"executionTime": 802,
			"startExecutionTime": 1562869318888,
			"endExecutionTime": 1562869318888
		},
		{
			"kernel": "CONV_2D",
			"executionTime": 2748,
			"startExecutionTime": 1562869318888,
			"endExecutionTime": 1562869318891
		},
		{
			"kernel": "DEPTHWISE_CONV_2D",
			"executionTime": 4590,
			"startExecutionTime": 1562869318891,
			"endExecutionTime": 1562869318896
		},
		{
			"kernel": "CONV_2D",
			"executionTime": 1393,
			"startExecutionTime": 1562869318896,
			"endExecutionTime": 1562869318897
		},
		{
			"kernel": "ADD",
			"executionTime": 4503,
			"startExecutionTime": 1562869318897,
			"endExecutionTime": 1562869318902
		},
		{
			"kernel": "CONV_2D",
			"executionTime": 2653,
			"startExecutionTime": 1562869318902,
			"endExecutionTime": 1562869318904
		},
		{
			"kernel": "DEPTHWISE_CONV_2D",
			"executionTime": 4600,
			"startExecutionTime": 1562869318904,
			"endExecutionTime": 1562869318909
		},
		{
			"kernel": "CONV_2D",
			"executionTime": 1346,
			"startExecutionTime": 1562869318909,
			"endExecutionTime": 1562869318910
		},
		{
			"kernel": "ADD",
			"executionTime": 4646,
			"startExecutionTime": 1562869318910,
			"endExecutionTime": 1562869318915
		},
		{
			"kernel": "CONV_2D",
			"executionTime": 2714,
			"startExecutionTime": 1562869318915,
			"endExecutionTime": 1562869318918
		},
		{
			"kernel": "DEPTHWISE_CONV_2D",
			"executionTime": 4534,
			"startExecutionTime": 1562869318918,
			"endExecutionTime": 1562869318922
		},
		{
			"kernel": "CONV_2D",
			"executionTime": 1586,
			"startExecutionTime": 1562869318922,
			"endExecutionTime": 1562869318924
		},
		{
			"kernel": "ADD",
			"executionTime": 4448,
			"startExecutionTime": 1562869318924,
			"endExecutionTime": 1562869318928
		},
		{
			"kernel": "CONV_2D",
			"executionTime": 2870,
			"startExecutionTime": 1562869318928,
			"endExecutionTime": 1562869318931
		},
		{
			"kernel": "DEPTHWISE_CONV_2D",
			"executionTime": 4456,
			"startExecutionTime": 1562869318931,
			"endExecutionTime": 1562869318936
		},
		{
			"kernel": "CONV_2D",
			"executionTime": 2121,
			"startExecutionTime": 1562869318936,
			"endExecutionTime": 1562869318938
		},
		{
			"kernel": "CONV_2D",
			"executionTime": 4633,
			"startExecutionTime": 1562869318938,
			"endExecutionTime": 1562869318942
		},
		{
			"kernel": "DEPTHWISE_CONV_2D",
			"executionTime": 6957,
			"startExecutionTime": 1562869318942,
			"endExecutionTime": 1562869318949
		},
		{
			"kernel": "CONV_2D",
			"executionTime": 2969,
			"startExecutionTime": 1562869318949,
			"endExecutionTime": 1562869318952
		},
		{
			"kernel": "ADD",
			"executionTime": 6659,
			"startExecutionTime": 1562869318952,
			"endExecutionTime": 1562869318959
		},
		{
			"kernel": "CONV_2D",
			"executionTime": 4566,
			"startExecutionTime": 1562869318959,
			"endExecutionTime": 1562869318964
		},
		{
			"kernel": "DEPTHWISE_CONV_2D",
			"executionTime": 7209,
			"startExecutionTime": 1562869318964,
			"endExecutionTime": 1562869318971
		},
		{
			"kernel": "CONV_2D",
			"executionTime": 2820,
			"startExecutionTime": 1562869318971,
			"endExecutionTime": 1562869318974
		},
		{
			"kernel": "ADD",
			"executionTime": 6712,
			"startExecutionTime": 1562869318974,
			"endExecutionTime": 1562869318980
		},
		{
			"kernel": "CONV_2D",
			"executionTime": 4656,
			"startExecutionTime": 1562869318980,
			"endExecutionTime": 1562869318985
		},
		{
			"kernel": "DEPTHWISE_CONV_2D",
			"executionTime": 1766,
			"startExecutionTime": 1562869318985,
			"endExecutionTime": 1562869318987
		},
		{
			"kernel": "CONV_2D",
			"executionTime": 1179,
			"startExecutionTime": 1562869318987,
			"endExecutionTime": 1562869318988
		},
		{
			"kernel": "CONV_2D",
			"executionTime": 2878,
			"startExecutionTime": 1562869318988,
			"endExecutionTime": 1562869318991
		},
		{
			"kernel": "DEPTHWISE_CONV_2D",
			"executionTime": 2586,
			"startExecutionTime": 1562869318991,
			"endExecutionTime": 1562869318993
		},
		{
			"kernel": "CONV_2D",
			"executionTime": 2108,
			"startExecutionTime": 1562869318993,
			"endExecutionTime": 1562869318996
		},
		{
			"kernel": "ADD",
			"executionTime": 2774,
			"startExecutionTime": 1562869318996,
			"endExecutionTime": 1562869318998
		},
		{
			"kernel": "CONV_2D",
			"executionTime": 2655,
			"startExecutionTime": 1562869318998,
			"endExecutionTime": 1562869319001
		},
		{
			"kernel": "DEPTHWISE_CONV_2D",
			"executionTime": 2653,
			"startExecutionTime": 1562869319001,
			"endExecutionTime": 1562869319004
		},
		{
			"kernel": "CONV_2D",
			"executionTime": 1973,
			"startExecutionTime": 1562869319004,
			"endExecutionTime": 1562869319006
		},
		{
			"kernel": "ADD",
			"executionTime": 2780,
			"startExecutionTime": 1562869319006,
			"endExecutionTime": 1562869319008
		},
		{
			"kernel": "CONV_2D",
			"executionTime": 2928,
			"startExecutionTime": 1562869319008,
			"endExecutionTime": 1562869319011
		},
		{
			"kernel": "DEPTHWISE_CONV_2D",
			"executionTime": 2664,
			"startExecutionTime": 1562869319011,
			"endExecutionTime": 1562869319014
		},
		{
			"kernel": "CONV_2D",
			"executionTime": 3648,
			"startExecutionTime": 1562869319014,
			"endExecutionTime": 1562869319018
		},
		{
			"kernel": "CONV_2D",
			"executionTime": 5598,
			"startExecutionTime": 1562869319018,
			"endExecutionTime": 1562869319023
		},
		{
			"kernel": "AVERAGE_POOL_2D",
			"executionTime": 219,
			"startExecutionTime": 1562869319023,
			"endExecutionTime": 1562869319024
		},
		{
			"kernel": "CONV_2D",
			"executionTime": 2270,
			"startExecutionTime": 1562869319024,
			"endExecutionTime": 1562869319026
		},
		{
			"kernel": "RESHAPE",
			"executionTime": 4,
			"startExecutionTime": 1562869319026,
			"endExecutionTime": 1562869319026
		}
	],
	"inferenceTime": 413542,
	"startInferenceTime": 1562869318612,
	"endInferenceTime": 1562869319026
}
