{
	"kernelMeasures": [
		{
			"kernel": "CONV_2D",
			"executionTime": 21135,
			"startExecutionTime": 1562865437610,
			"endExecutionTime": 1562865437632
		},
		{
			"kernel": "DEPTHWISE_CONV_2D",
			"executionTime": 31918,
			"startExecutionTime": 1562865437632,
			"endExecutionTime": 1562865437664
		},
		{
			"kernel": "CONV_2D",
			"executionTime": 6452,
			"startExecutionTime": 1562865437664,
			"endExecutionTime": 1562865437670
		},
		{
			"kernel": "CONV_2D",
			"executionTime": 31884,
			"startExecutionTime": 1562865437670,
			"endExecutionTime": 1562865437702
		},
		{
			"kernel": "DEPTHWISE_CONV_2D",
			"executionTime": 21485,
			"startExecutionTime": 1562865437702,
			"endExecutionTime": 1562865437723
		},
		{
			"kernel": "CONV_2D",
			"executionTime": 3444,
			"startExecutionTime": 1562865437723,
			"endExecutionTime": 1562865437727
		},
		{
			"kernel": "CONV_2D",
			"executionTime": 13642,
			"startExecutionTime": 1562865437727,
			"endExecutionTime": 1562865437741
		},
		{
			"kernel": "DEPTHWISE_CONV_2D",
			"executionTime": 28767,
			"startExecutionTime": 1562865437741,
			"endExecutionTime": 1562865437769
		},
		{
			"kernel": "CONV_2D",
			"executionTime": 4275,
			"startExecutionTime": 1562865437769,
			"endExecutionTime": 1562865437774
		},
		{
			"kernel": "ADD",
			"executionTime": 26487,
			"startExecutionTime": 1562865437774,
			"endExecutionTime": 1562865437800
		},
		{
			"kernel": "CONV_2D",
			"executionTime": 14569,
			"startExecutionTime": 1562865437800,
			"endExecutionTime": 1562865437815
		},
		{
			"kernel": "DEPTHWISE_CONV_2D",
			"executionTime": 7445,
			"startExecutionTime": 1562865437815,
			"endExecutionTime": 1562865437822
		},
		{
			"kernel": "CONV_2D",
			"executionTime": 1359,
			"startExecutionTime": 1562865437822,
			"endExecutionTime": 1562865437824
		},
		{
			"kernel": "CONV_2D",
			"executionTime": 4446,
			"startExecutionTime": 1562865437824,
			"endExecutionTime": 1562865437828
		},
		{
			"kernel": "DEPTHWISE_CONV_2D",
			"executionTime": 9735,
			"startExecutionTime": 1562865437828,
			"endExecutionTime": 1562865437838
		},
		{
			"kernel": "CONV_2D",
			"executionTime": 1717,
			"startExecutionTime": 1562865437838,
			"endExecutionTime": 1562865437839
		},
		{
			"kernel": "ADD",
			"executionTime": 8782,
			"startExecutionTime": 1562865437839,
			"endExecutionTime": 1562865437848
		},
		{
			"kernel": "CONV_2D",
			"executionTime": 4519,
			"startExecutionTime": 1562865437848,
			"endExecutionTime": 1562865437853
		},
		{
			"kernel": "DEPTHWISE_CONV_2D",
			"executionTime": 9417,
			"startExecutionTime": 1562865437853,
			"endExecutionTime": 1562865437862
		},
		{
			"kernel": "CONV_2D",
			"executionTime": 1631,
			"startExecutionTime": 1562865437862,
			"endExecutionTime": 1562865437864
		},
		{
			"kernel": "ADD",
			"executionTime": 8822,
			"startExecutionTime": 1562865437864,
			"endExecutionTime": 1562865437873
		},
		{
			"kernel": "CONV_2D",
			"executionTime": 4448,
			"startExecutionTime": 1562865437873,
			"endExecutionTime": 1562865437877
		},
		{
			"kernel": "DEPTHWISE_CONV_2D",
			"executionTime": 2525,
			"startExecutionTime": 1562865437877,
			"endExecutionTime": 1562865437880
		},
		{
			"kernel": "CONV_2D",
			"executionTime": 827,
			"startExecutionTime": 1562865437880,
			"endExecutionTime": 1562865437881
		},
		{
			"kernel": "CONV_2D",
			"executionTime": 2639,
			"startExecutionTime": 1562865437881,
			"endExecutionTime": 1562865437883
		},
		{
			"kernel": "DEPTHWISE_CONV_2D",
			"executionTime": 4502,
			"startExecutionTime": 1562865437883,
			"endExecutionTime": 1562865437888
		},
		{
			"kernel": "CONV_2D",
			"executionTime": 1403,
			"startExecutionTime": 1562865437888,
			"endExecutionTime": 1562865437889
		},
		{
			"kernel": "ADD",
			"executionTime": 4437,
			"startExecutionTime": 1562865437889,
			"endExecutionTime": 1562865437894
		},
		{
			"kernel": "CONV_2D",
			"executionTime": 2625,
			"startExecutionTime": 1562865437894,
			"endExecutionTime": 1562865437896
		},
		{
			"kernel": "DEPTHWISE_CONV_2D",
			"executionTime": 4547,
			"startExecutionTime": 1562865437896,
			"endExecutionTime": 1562865437901
		},
		{
			"kernel": "CONV_2D",
			"executionTime": 1391,
			"startExecutionTime": 1562865437901,
			"endExecutionTime": 1562865437902
		},
		{
			"kernel": "ADD",
			"executionTime": 4382,
			"startExecutionTime": 1562865437902,
			"endExecutionTime": 1562865437907
		},
		{
			"kernel": "CONV_2D",
			"executionTime": 2635,
			"startExecutionTime": 1562865437907,
			"endExecutionTime": 1562865437909
		},
		{
			"kernel": "DEPTHWISE_CONV_2D",
			"executionTime": 4434,
			"startExecutionTime": 1562865437909,
			"endExecutionTime": 1562865437914
		},
		{
			"kernel": "CONV_2D",
			"executionTime": 1398,
			"startExecutionTime": 1562865437914,
			"endExecutionTime": 1562865437915
		},
		{
			"kernel": "ADD",
			"executionTime": 4425,
			"startExecutionTime": 1562865437915,
			"endExecutionTime": 1562865437919
		},
		{
			"kernel": "CONV_2D",
			"executionTime": 2621,
			"startExecutionTime": 1562865437919,
			"endExecutionTime": 1562865437922
		},
		{
			"kernel": "DEPTHWISE_CONV_2D",
			"executionTime": 4353,
			"startExecutionTime": 1562865437922,
			"endExecutionTime": 1562865437926
		},
		{
			"kernel": "CONV_2D",
			"executionTime": 2068,
			"startExecutionTime": 1562865437926,
			"endExecutionTime": 1562865437929
		},
		{
			"kernel": "CONV_2D",
			"executionTime": 4546,
			"startExecutionTime": 1562865437929,
			"endExecutionTime": 1562865437933
		},
		{
			"kernel": "DEPTHWISE_CONV_2D",
			"executionTime": 6818,
			"startExecutionTime": 1562865437933,
			"endExecutionTime": 1562865437940
		},
		{
			"kernel": "CONV_2D",
			"executionTime": 2861,
			"startExecutionTime": 1562865437940,
			"endExecutionTime": 1562865437943
		},
		{
			"kernel": "ADD",
			"executionTime": 6613,
			"startExecutionTime": 1562865437943,
			"endExecutionTime": 1562865437949
		},
		{
			"kernel": "CONV_2D",
			"executionTime": 4507,
			"startExecutionTime": 1562865437949,
			"endExecutionTime": 1562865437954
		},
		{
			"kernel": "DEPTHWISE_CONV_2D",
			"executionTime": 6804,
			"startExecutionTime": 1562865437954,
			"endExecutionTime": 1562865437961
		},
		{
			"kernel": "CONV_2D",
			"executionTime": 2753,
			"startExecutionTime": 1562865437961,
			"endExecutionTime": 1562865437963
		},
		{
			"kernel": "ADD",
			"executionTime": 6603,
			"startExecutionTime": 1562865437963,
			"endExecutionTime": 1562865437970
		},
		{
			"kernel": "CONV_2D",
			"executionTime": 4498,
			"startExecutionTime": 1562865437970,
			"endExecutionTime": 1562865437975
		},
		{
			"kernel": "DEPTHWISE_CONV_2D",
			"executionTime": 1720,
			"startExecutionTime": 1562865437975,
			"endExecutionTime": 1562865437976
		},
		{
			"kernel": "CONV_2D",
			"executionTime": 1228,
			"startExecutionTime": 1562865437976,
			"endExecutionTime": 1562865437978
		},
		{
			"kernel": "CONV_2D",
			"executionTime": 2750,
			"startExecutionTime": 1562865437978,
			"endExecutionTime": 1562865437980
		},
		{
			"kernel": "DEPTHWISE_CONV_2D",
			"executionTime": 2514,
			"startExecutionTime": 1562865437980,
			"endExecutionTime": 1562865437983
		},
		{
			"kernel": "CONV_2D",
			"executionTime": 1926,
			"startExecutionTime": 1562865437983,
			"endExecutionTime": 1562865437985
		},
		{
			"kernel": "ADD",
			"executionTime": 2735,
			"startExecutionTime": 1562865437985,
			"endExecutionTime": 1562865437988
		},
		{
			"kernel": "CONV_2D",
			"executionTime": 2678,
			"startExecutionTime": 1562865437988,
			"endExecutionTime": 1562865437990
		},
		{
			"kernel": "DEPTHWISE_CONV_2D",
			"executionTime": 2588,
			"startExecutionTime": 1562865437990,
			"endExecutionTime": 1562865437993
		},
		{
			"kernel": "CONV_2D",
			"executionTime": 1944,
			"startExecutionTime": 1562865437993,
			"endExecutionTime": 1562865437995
		},
		{
			"kernel": "ADD",
			"executionTime": 2733,
			"startExecutionTime": 1562865437995,
			"endExecutionTime": 1562865437997
		},
		{
			"kernel": "CONV_2D",
			"executionTime": 2680,
			"startExecutionTime": 1562865437998,
			"endExecutionTime": 1562865438000
		},
		{
			"kernel": "DEPTHWISE_CONV_2D",
			"executionTime": 2602,
			"startExecutionTime": 1562865438000,
			"endExecutionTime": 1562865438003
		},
		{
			"kernel": "CONV_2D",
			"executionTime": 3598,
			"startExecutionTime": 1562865438003,
			"endExecutionTime": 1562865438006
		},
		{
			"kernel": "CONV_2D",
			"executionTime": 5456,
			"startExecutionTime": 1562865438006,
			"endExecutionTime": 1562865438012
		},
		{
			"kernel": "AVERAGE_POOL_2D",
			"executionTime": 217,
			"startExecutionTime": 1562865438012,
			"endExecutionTime": 1562865438012
		},
		{
			"kernel": "CONV_2D",
			"executionTime": 2121,
			"startExecutionTime": 1562865438012,
			"endExecutionTime": 1562865438014
		},
		{
			"kernel": "RESHAPE",
			"executionTime": 3,
			"startExecutionTime": 1562865438014,
			"endExecutionTime": 1562865438014
		}
	],
	"inferenceTime": 403768,
	"startInferenceTime": 1562865437610,
	"endInferenceTime": 1562865438014
}
